{
"translations":{
	"id1":{
		"en":"able",
		"kr":"kapav"
	},
	"id2":{
		"en":"accept",
		"kr":"aksepte, aksept"
	},
	"id3":{
		"en":"accompany",
		"kr":"akonpagne, akonpagn"
	},
	"id4":{
		"en":"adjust",
		"kr":"aziste, azist"
	},
	"id5":{
		"en":"admire",
		"kr":"admire, admir"
	},
	"id6":{
		"en":"advise",
		"kr":"konseye, konsey"
	},
	"id7":{
		"en":"afraid",
		"kr":"gagn per"
	},
	"id8":{
		"en":"allow",
		"kr":"permet"
	},
	"id9":{
		"en":"annoy",
		"kr":"agase, agas"
	},
	"id10":{
		"en":"answer",
		"kr":"reponn"
	},
	"id11":{
		"en":"appear",
		"kr":"aparet or paret"
	},
	"id12":{
		"en":"apply",
		"kr":"aplike, aplik"
	},
	"id13":{
		"en":"approach",
		"kr":"koste"
	},
	"id14":{
		"en":"assure",
		"kr":"asire, asir"
	},
	"id15":{
		"en":"bathe",
		"kr":"lave, lav"
	},
	"id16":{
		"en":"be",
		"kr":"ete"
	},
	"id17":{
		"en":"beat",
		"kr":"bate, bat"
	},
	"id18":{
		"en":"become",
		"kr":"devini or vini"
	},
	"id19":{
		"en":"begin",
		"kr":"koumanse, koumans"
	},
	"id20":{
		"en":"bite",
		"kr":"morde, mord"
	},
	"id21":{
		"en":"blame",
		"kr":"blame, blam"
	},
	"id22":{
		"en":"blow",
		"kr":"soufle"
	},
	"id23":{
		"en":"boast",
		"kr":"flate, flat"
	},
	"id24":{
		"en":"boil",
		"kr":"bwi"
	},
	"id25":{
		"en":"boost",
		"kr":"stimile, stimil"
	},
	"id26":{
		"en":"bored",
		"kr":" agase, agas"
	},
	"id27":{
		"en":"borrow",
		"kr":"anprinte, anprint"
	},
	"id28":{
		"en":"bother",
		"kr":"amerde, amerd"
	},
	"id29":{
		"en":"bow",
		"kr":"inkline, inklin"
	},
	"id30":{
		"en":"breathe",
		"kr":"repire, respir"
	},
	"id31":{
		"en":"bring",
		"kr":"amene, amen"
	},
	"id32":{
		"en":"broken",
		"kr":"kase, kas"
	},
	"id33":{
		"en":"brush",
		"kr":"brose, bros"
	},
	"id34":{
		"en":"build",
		"kr":"aranze, aranz or ranze,ranz"
	},
	"id35":{
		"en":"burn",
		"kr":"brile, bril"
	},
	"id36":{
		"en":"burst",
		"kr":"eklate, eklat"
	},
	"id37":{
		"en":"bury",
		"kr":"antere, anter"
	},
	"id38":{
		"en":"can",
		"kr":"kapav"
	},
	"id39":{
		"en":"cancel",
		"kr":"kensel"
	},
	"id40":{
		"en":"caress",
		"kr":"karese, karess"
	},
	"id41":{
		"en":"carry",
		"kr":"sarye"
	},
	"id42":{
		"en":"carve",
		"kr":"grave, grav"
	},
	"id43":{
		"en":"catch",
		"kr":"atrape, atrap or maye,may"
	},
	"id44":{
		"en":"chain",
		"kr":"ansene, ansenn"
	},
	"id45":{
		"en":"change",
		"kr":"sanze, sanz"
	},
	"id46":{
		"en":"chase",
		"kr":"pouse, pous"
	},
	"id47":{
		"en":"cheat",
		"kr":"frode, frod or trike, trik"
	},
	"id48":{
		"en":"chew",
		"kr":"masse, mass or moule,moul"
	},
	"id49":{
		"en":"choose",
		"kr":"swazir"
	},
	"id50":{
		"en":"circle",
		"kr":"anserkle"
	},
	"id51":{
		"en":"claim",
		"kr":"reklame, reklam"
	},
	"id52":{
		"en":"classify",
		"kr":"klasifie"
	},
	"id53":{
		"en":"clean",
		"kr":"netwaye, netway"
	},
	"id54":{
		"en":"clear",
		"kr":"efase, efas"
	},
	"id55":{
		"en":"climb",
		"kr":"grinpe, grinp"
	},
	"id56":{
		"en":"close",
		"kr":"ferme, ferm"
	},
	"id57":{
		"en":"collapse",
		"kr":"tonbe, tom"
	},
	"id58":{
		"en":"collect",
		"kr":"kolekte"
	},
	"id59":{
		"en":"collide",
		"kr":"tape, tap"
	},
	"id60":{
		"en":"come",
		"kr":"vini"
	},
	"id61":{
		"en":"complain",
		"kr":"plengne, plengn"
	},
	"id62":{
		"en":"complete",
		"kr":"konplete, konplet"
	},
	"id63":{
		"en":"compress",
		"kr":"konpresse, konpress"
	},
	"id64":{
		"en":"concern",
		"kr":"konserne, konsern"
	},
	"id65":{
		"en":"confuse",
		"kr":"abriti"
	},
	"id66":{
		"en":"congratulate",
		"kr":"felisite, felisit"
	},
	"id67":{
		"en":"consent",
		"kr":"aksepte, aksept"
	},
	"id68":{
		"en":"consult",
		"kr":"konsilte"
	},
	"id69":{
		"en":"control",
		"kr":"kontrole, kontrol"
	},
	"id70":{
		"en":"cook",
		"kr":"kwi"
	},
	"id71":{
		"en":"copy",
		"kr":"kopie"
	},
	"id72":{
		"en":"correct",
		"kr":"korize, koriz"
	},
	"id73":{
		"en":"cough",
		"kr":"touse, tous"
	},
	"id74":{
		"en":"count",
		"kr":"konte, kont"
	},
	"id75":{
		"en":"cover",
		"kr":"kouver"
	},
	"id76":{
		"en":"crawl",
		"kr":"ranpe, ranp"
	},
	"id77":{
		"en":"create",
		"kr":"kree"
	},
	"id78":{
		"en":"crouch",
		"kr":"asize lor lipie"
	},
	"id79":{
		"en":"crumple",
		"kr":"frwase, frwas"
	},
	"id80":{
		"en":"crush",
		"kr":"frwase, frwas or kraze,kraz"
	},
	"id81":{
		"en":"cry",
		"kr":"plore, plor"
	},
	"id82":{
		"en":"cut",
		"kr":"koupe, koup"
	},
	"id83":{
		"en":"damage",
		"kr":"andomaze, andomaz"
	},
	"id84":{
		"en":"dance",
		"kr":"danse, dans"
	},
	"id85":{
		"en":"dare",
		"kr":"oze, oz"
	},
	"id86":{
		"en":"deal",
		"kr":"gagn zafer avek"
	},
	"id87":{
		"en":"deceive",
		"kr":"anbete, anbet"
	},
	"id88":{
		"en":"decide",
		"kr":"deside, desid"
	},
	"id89":{
		"en":"declare",
		"kr":"deklare, deklar"
	},
	"id90":{
		"en":"decorate",
		"kr":"dekore, dekor"
	},
	"id91":{
		"en":"decrease",
		"kr":"diminie"
	},
	"id92":{
		"en":"defend",
		"kr":"defann"
	},
	"id93":{
		"en":"dehydrate",
		"kr":"dezidrate, dezidrat"
	},
	"id94":{
		"en":"delete",
		"kr":"efase, efas"
	},
	"id95":{
		"en":"deliver",
		"kr":"livre"
	},
	"id96":{
		"en":"demonstrate",
		"kr":"demontre or montre"
	},
	"id97":{
		"en":"depend",
		"kr":"depann"
	},
	"id98":{
		"en":"descend",
		"kr":"desann"
	},
	"id99":{
		"en":"desire",
		"kr":"desire, desir"
	},
	"id100":{
		"en":"despise",
		"kr":"meprize, mepriz"
	},
	"id101":{
		"en":"destroy",
		"kr":"touye, touy"
	},
	"id102":{
		"en":"develop",
		"kr":"devlope, devlop"
	},
	"id103":{
		"en":"die",
		"kr":"mor"
	},
	"id104":{
		"en":"differ",
		"kr":"ki diferan ar"
	},
	"id105":{
		"en":"dig",
		"kr":"fouye, fouy"
	},
	"id106":{
		"en":"digest",
		"kr":"dizere, dizer"
	},
	"id107":{
		"en":"direct",
		"kr":"donn direksion"
	},
	"id108":{
		"en":"disagree",
		"kr":"pa dakor"
	},
	"id109":{
		"en":"disappear",
		"kr":"disparet"
	},
	"id110":{
		"en":"discuss",
		"kr":"diskite, diskit"
	},
	"id111":{
		"en":"dislike",
		"kr":"pa kontan"
	},
	"id112":{
		"en":"disperse",
		"kr":"disperse, dispers or"
	},
	"id113":{
		"en":"fane",
		"kr":" fann"
	},
	"id114":{
		"en":"dispute",
		"kr":"diskite, diskit"
	},
	"id115":{
		"en":"distribute",
		"kr":"distribie"
	},
	"id116":{
		"en":"dive",
		"kr":"plonze, plonz"
	},
	"id117":{
		"en":"divide",
		"kr":"divize, diviz"
	},
	"id118":{
		"en":"do",
		"kr":"fer"
	},
	"id119":{
		"en":"drag",
		"kr":"tire, tir"
	},
	"id120":{
		"en":"draw",
		"kr":"desine, desinn"
	},
	"id121":{
		"en":"dream",
		"kr":"reve, rev"
	},
	"id122":{
		"en":"dress",
		"kr":"abiye, abiy"
	},
	"id123":{
		"en":"dribble",
		"kr":"reye, rey"
	},
	"id124":{
		"en":"drink",
		"kr":"bwar"
	},
	"id125":{
		"en":"drip",
		"kr":"koule, koul"
	},
	"id126":{
		"en":"drive",
		"kr":"kondire, kondir"
	},
	"id127":{
		"en":"drool",
		"kr":"bave, bav"
	},
	"id128":{
		"en":"drop",
		"kr":"large, larg"
	},
	"id129":{
		"en":"drop",
		"kr":"lestonbe"
	},
	"id130":{
		"en":"dry",
		"kr":"fer sek or met sek"
	},
	"id131":{
		"en":"eat",
		"kr":"manze, manz"
	},
	"id132":{
		"en":"educate",
		"kr":"edike, edik"
	},
	"id133":{
		"en":"eject",
		"kr":"ezekte"
	},
	"id134":{
		"en":"embarrass",
		"kr":"anbarase, anbaras"
	},
	"id135":{
		"en":"embrace",
		"kr":"anbrase, anbras"
	},
	"id136":{
		"en":"encourage",
		"kr":"ankouraze, ankouraz"
	},
	"id137":{
		"en":"enter",
		"kr":"rantre, rant"
	},
	"id138":{
		"en":"escape",
		"kr":"sove, sov"
	},
	"id139":{
		"en":"exaggerate",
		"kr":"exazere, exazer"
	},
	"id140":{
		"en":"exchange",
		"kr":"esanze, esanz"
	},
	"id141":{
		"en":"exist",
		"kr":"existe, exist"
	},
	"id142":{
		"en":"expect",
		"kr":"atann"
	},
	"id143":{
		"en":"experience",
		"kr":"fer lexperyans"
	},
	"id144":{
		"en":"explode",
		"kr":"eklate, eklat or exploze,"
	},
	"id145":{
		"en":"exploz",
		"kr":""
	},
	"id146":{
		"en":"fish",
		"kr":"lapes"
	},
	"id147":{
		"en":"fall",
		"kr":"tonbe, tom"
	},
	"id148":{
		"en":"forget",
		"kr":"bliye"
	},
	"id149":{
		"en":"fun",
		"kr":"fer gamat"
	},
	"id150":{
		"en":"get",
		"kr":"gagne, gagn"
	},
	"id151":{
		"en":"give",
		"kr":"donne, donn"
	},
	"id152":{
		"en":"go",
		"kr":"ale, al"
	},
	"id153":{
		"en":"grasp",
		"kr":"trape, trap"
	},
	"id154":{
		"en":"greet",
		"kr":"salie"
	},
	"id155":{
		"en":"grind",
		"kr":"kraze, kraz"
	},
	"id156":{
		"en":"grip",
		"kr":"sezi"
	},
	"id157":{
		"en":"guard",
		"kr":"veye, vey"
	},
	"id158":{
		"en":"hide",
		"kr":"kasiet"
	},
	"id159":{
		"en":"hope",
		"kr":"espere, esper"
	},
	"id160":{
		"en":"irritate",
		"kr":"agase, agas"
	},
	"id161":{
		"en":"join",
		"kr":"zwenn"
	},
	"id162":{
		"en":"jump",
		"kr":"sote, sot"
	},
	"id163":{
		"en":"justify",
		"kr":"zistifie"
	},
	"id164":{
		"en":"keep",
		"kr":"garde, gard"
	},
	"id165":{
		"en":"kiss",
		"kr":"anbrase, anbras or ba"
	},
	"id166":{
		"en":"kneel",
		"kr":" azenou"
	},
	"id167":{
		"en":"knock",
		"kr":"tape, tap"
	},
	"id168":{
		"en":"know",
		"kr":"kone, konn"
	},
	"id169":{
		"en":"leak",
		"kr":"koule, koul"
	},
	"id170":{
		"en":"lift",
		"kr":"leve, lev"
	},
	"id171":{
		"en":"magnify",
		"kr":"grosi"
	},
	"id172":{
		"en":"maintain",
		"kr":"mintenir"
	},
	"id173":{
		"en":"make",
		"kr":"fabrike, fabric or fer"
	},
	"id174":{
		"en":"manage",
		"kr":"dirize, diriz"
	},
	"id175":{
		"en":"mark",
		"kr":"marke, mark"
	},
	"id176":{
		"en":"mark",
		"kr":"korize, koriz"
	},
	"id177":{
		"en":"marry",
		"kr":"marye"
	},
	"id178":{
		"en":"mean",
		"kr":"sinifie, sinifi"
	},
	"id179":{
		"en":"measure",
		"kr":"mezire, mezir"
	},
	"id180":{
		"en":"meet",
		"kr":"zwenn"
	},
	"id181":{
		"en":"memorise",
		"kr":"memorize, memoriz"
	},
	"id182":{
		"en":"mention",
		"kr":"mansione, mansionn"
	},
	"id183":{
		"en":"merge",
		"kr":"zwenn"
	},
	"id184":{
		"en":"migrate",
		"kr":"emigre"
	},
	"id185":{
		"en":"mind",
		"kr":"anbarase, anbaras"
	},
	"id186":{
		"en":"mingle",
		"kr":"melanze avek"
	},
	"id187":{
		"en":"minimise",
		"kr":"minimize, minimiz"
	},
	"id188":{
		"en":"miss",
		"kr":"manke, mank"
	},
	"id189":{
		"en":"miss",
		"kr":"rate, rat"
	},
	"id190":{
		"en":"misunderstand",
		"kr":"mal konpran or tronpe,"
	},
	"id191":{
		"en":"tronp",
		"kr":""
	},
	"id192":{
		"en":"mix",
		"kr":"melanze, melanz"
	},
	"id193":{
		"en":"mix",
		"kr":"up briye"
	},
	"id194":{
		"en":"moan",
		"kr":"plengne, plengn"
	},
	"id195":{
		"en":"motivate",
		"kr":"motive, motiv"
	},
	"id196":{
		"en":"mould",
		"kr":"moule, moul"
	},
	"id197":{
		"en":"mount",
		"kr":"monte lor"
	},
	"id198":{
		"en":"move",
		"kr":"bouze, bouz"
	},
	"id199":{
		"en":"move",
		"kr":" deplase, deplas"
	},
	"id200":{
		"en":"move",
		"kr":"avanse, avans"
	},
	"id201":{
		"en":"muddle",
		"kr":"anbrouye"
	},
	"id202":{
		"en":"multiply",
		"kr":"miltipliye, miltipliy"
	},
	"id203":{
		"en":"murmur",
		"kr":"mirmire, mirmir"
	},
	"id204":{
		"en":"muster",
		"kr":"rasanble, rasanbl"
	},
	"id205":{
		"en":"mutter",
		"kr":"grogne, grogn"
	},
	"id206":{
		"en":"name",
		"kr":"apele, apel"
	},
	"id207":{
		"en":"navigate",
		"kr":"navige"
	},
	"id208":{
		"en":"need",
		"kr":"bizin"
	},
	"id209":{
		"en":"neglect",
		"kr":"neglize, negliz"
	},
	"id210":{
		"en":"nip",
		"kr":"pinse, pins"
	},
	"id211":{
		"en":"note",
		"kr":"note, not"
	},
	"id212":{
		"en":"notice",
		"kr":"remarke, remark"
	},
	"id213":{
		"en":"notify",
		"kr":"notifie"
	},
	"id214":{
		"en":"obey",
		"kr":"obeir"
	},
	"id215":{
		"en":"oblige",
		"kr":"oblize, obliz"
	},
	"id216":{
		"en":"observe",
		"kr":"obzerve, observ"
	},
	"id217":{
		"en":"obstruct",
		"kr":"bloke, blok"
	},
	"id218":{
		"en":"obtain",
		"kr":"gagne, gagn"
	},
	"id219":{
		"en":"occupy",
		"kr":"okipe, okip"
	},
	"id220":{
		"en":"occur",
		"kr":"arive, ariv"
	},
	"id221":{
		"en":"offend",
		"kr":"ofanse, ofans"
	},
	"id222":{
		"en":"offer",
		"kr":"done, donn"
	},
	"id223":{
		"en":"operate",
		"kr":"opere, oper"
	},
	"id224":{
		"en":"oppose",
		"kr":"opoze, opoz"
	},
	"id225":{
		"en":"organise",
		"kr":"organize, organiz"
	},
	"id226":{
		"en":"overdo",
		"kr":"exazere, exazer"
	},
	"id227":{
		"en":"overtake",
		"kr":"depasse, depass"
	},
	"id228":{
		"en":"own",
		"kr":"posede, posed"
	},
	"id229":{
		"en":"pacify",
		"kr":"kalme"
	},
	"id230":{
		"en":"pack",
		"kr":"anbale, anbal or ranpli"
	},
	"id231":{
		"en":"paint",
		"kr":"pintire, pintir"
	},
	"id232":{
		"en":"pant",
		"kr":"respire avek difikilte"
	},
	"id233":{
		"en":"paralyse",
		"kr":"paralize, paraliz"
	},
	"id234":{
		"en":"pardon",
		"kr":"pardone, pardonn"
	},
	"id235":{
		"en":"pardon",
		"kr":"exkize, exkiz"
	},
	"id236":{
		"en":"part",
		"kr":"separe, separ"
	},
	"id237":{
		"en":"participate",
		"kr":"partisipe, partisip"
	},
	"id238":{
		"en":"pass",
		"kr":"pase, pass"
	},
	"id239":{
		"en":"pat",
		"kr":"tape, tap"
	},
	"id240":{
		"en":"pay",
		"kr":"peye, pey"
	},
	"id241":{
		"en":"peek",
		"kr":"louke, louk"
	},
	"id242":{
		"en":"peel",
		"kr":"plise, plis"
	},
	"id243":{
		"en":"peep",
		"kr":"louke, louk"
	},
	"id244":{
		"en":"persevere",
		"kr":"persevere"
	},
	"id245":{
		"en":"persuade",
		"kr":"konvink"
	},
	"id246":{
		"en":"pick",
		"kr":"ramase, ramas"
	},
	"id247":{
		"en":"pick",
		"kr":"up ramase, ramas"
	},
	"id248":{
		"en":"pierce",
		"kr":"perse, pers"
	},
	"id249":{
		"en":"plant",
		"kr":"plante, plant"
	},
	"id250":{
		"en":"play",
		"kr":"zwe"
	},
	"id251":{
		"en":"pluck",
		"kr":"kase, kas"
	},
	"id252":{
		"en":"polish",
		"kr":"poli"
	},
	"id253":{
		"en":"pour",
		"kr":"vide, vid"
	},
	"id254":{
		"en":"pray",
		"kr":"priye"
	},
	"id255":{
		"en":"precede",
		"kr":"presede, presed"
	},
	"id256":{
		"en":"precipitate",
		"kr":"presipite, presipit"
	},
	"id257":{
		"en":"precise",
		"kr":"presize, presiz"
	},
	"id258":{
		"en":"prepare",
		"kr":"prepare, prepar"
	},
	"id259":{
		"en":"prescribe",
		"kr":"preskrir"
	},
	"id260":{
		"en":"preserve",
		"kr":"preserve, preserv"
	},
	"id261":{
		"en":"pretend",
		"kr":"fer samblan"
	},
	"id262":{
		"en":"prevent",
		"kr":"prevenir"
	},
	"id263":{
		"en":"produce",
		"kr":"prodir"
	},
	"id264":{
		"en":"progress",
		"kr":"progrese, progres"
	},
	"id265":{
		"en":"prohibit",
		"kr":"interdi"
	},
	"id266":{
		"en":"promise",
		"kr":"promet"
	},
	"id267":{
		"en":"protect",
		"kr":"proteze, protez"
	},
	"id268":{
		"en":"protest",
		"kr":"proteste, protest"
	},
	"id269":{
		"en":"prove",
		"kr":"prouve, prouv"
	},
	"id270":{
		"en":"provide",
		"kr":"fourni"
	},
	"id271":{
		"en":"provoke",
		"kr":"agase, agas"
	},
	"id272":{
		"en":"pull",
		"kr":"rise, ris or tire, tir"
	},
	"id273":{
		"en":"push",
		"kr":"pouse, pous"
	},
	"id274":{
		"en":"put",
		"kr":"mete, met"
	},
	"id275":{
		"en":"quantify",
		"kr":"mizire, mizir"
	},
	"id276":{
		"en":"quarrel",
		"kr":"lager"
	},
	"id277":{
		"en":"query",
		"kr":"demann"
	},
	"id278":{
		"en":"quit",
		"kr":"kite, kit"
	},
	"id279":{
		"en":"raze",
		"kr":"raze, raz"
	},
	"id280":{
		"en":"reach",
		"kr":"arive, ariv"
	},
	"id281":{
		"en":"read",
		"kr":"lir"
	},
	"id282":{
		"en":"ready",
		"kr":"pare"
	},
	"id283":{
		"en":"realise",
		"kr":"realize, realiz"
	},
	"id284":{
		"en":"recall",
		"kr":"rapel"
	},
	"id285":{
		"en":"receive",
		"kr":"resevwar"
	},
	"id286":{
		"en":"recharge",
		"kr":"resarze"
	},
	"id287":{
		"en":"reclaim",
		"kr":"reklame, reklam"
	},
	"id288":{
		"en":"recline",
		"kr":"inkline, inklin"
	},
	"id289":{
		"en":"recognise",
		"kr":"rekonet"
	},
	"id290":{
		"en":"recommend",
		"kr":"rekomande, rekomand"
	},
	"id291":{
		"en":"record",
		"kr":"anrezistre, anrezistr"
	},
	"id292":{
		"en":"recover",
		"kr":"degaze"
	},
	"id293":{
		"en":"reduce",
		"kr":"diminie"
	},
	"id294":{
		"en":"reflect",
		"kr":"reflekte, reflekt"
	},
	"id295":{
		"en":"refuse",
		"kr":"refize, refiz"
	},
	"id296":{
		"en":"regret",
		"kr":"regrete, regret"
	},
	"id297":{
		"en":"relax",
		"kr":"dekontrakte"
	},
	"id298":{
		"en":"remain",
		"kr":"reste, rest"
	},
	"id299":{
		"en":"remember",
		"kr":"rapel"
	},
	"id300":{
		"en":"remove",
		"kr":"tire, tir"
	},
	"id301":{
		"en":"rent",
		"kr":"lwe"
	},
	"id302":{
		"en":"repair",
		"kr":"repare, repar"
	},
	"id303":{
		"en":"repeat",
		"kr":"repete, repet"
	},
	"id304":{
		"en":"resemble",
		"kr":"resanble, resanbl"
	},
	"id305":{
		"en":"rest",
		"kr":"repoze, repoz"
	},
	"id306":{
		"en":"restrain",
		"kr":"anpese, anpes"
	},
	"id307":{
		"en":"return",
		"kr":"retourne, retourn"
	},
	"id308":{
		"en":"reward",
		"kr":"rekompanse, rekompans"
	},
	"id309":{
		"en":"rinse",
		"kr":"rinse, rins"
	},
	"id310":{
		"en":"rip",
		"kr":"desire, desir"
	},
	"id311":{
		"en":"rotate",
		"kr":"pivote"
	},
	"id312":{
		"en":"rub",
		"kr":"frote, frot"
	},
	"id313":{
		"en":"ruin",
		"kr":"rwine, rwin"
	},
	"id314":{
		"en":"run",
		"kr":"galoupe, galoup"
	},
	"id315":{
		"en":"rush",
		"kr":"degaze, degaz"
	},
	"id316":{
		"en":"save",
		"kr":"sape, sap"
	},
	"id317":{
		"en":"save",
		"kr":"ekonomize, ekonomiz"
	},
	"id318":{
		"en":"say",
		"kr":"dir"
	},
	"id319":{
		"en":"scare",
		"kr":"fer per"
	},
	"id320":{
		"en":"scratch",
		"kr":"grate, grat"
	},
	"id321":{
		"en":"seal",
		"kr":"sele"
	},
	"id322":{
		"en":"search",
		"kr":"rode, rod"
	},
	"id323":{
		"en":"see",
		"kr":"trouve, trouv"
	},
	"id324":{
		"en":"seek",
		"kr":"rode, rod"
	},
	"id325":{
		"en":"seem",
		"kr":"paret"
	},
	"id326":{
		"en":"seize",
		"kr":"sezi"
	},
	"id327":{
		"en":"sell",
		"kr":"vande, vann"
	},
	"id328":{
		"en":"send",
		"kr":"anvwaye, anvway or"
	},
	"id329":{
		"en":"avoye",
		"kr":" avoy"
	},
	"id330":{
		"en":"separate",
		"kr":"separe, separ"
	},
	"id331":{
		"en":"settle",
		"kr":"etabli"
	},
	"id332":{
		"en":"sew",
		"kr":"koud"
	},
	"id333":{
		"en":"shake",
		"kr":"sakouye, sakouy"
	},
	"id334":{
		"en":"share",
		"kr":"partaze, partaz"
	},
	"id335":{
		"en":"sharpen",
		"kr":"fite, fit"
	},
	"id336":{
		"en":"shatter",
		"kr":"kase, kass"
	},
	"id337":{
		"en":"shave",
		"kr":"raze, raz"
	},
	"id338":{
		"en":"shine",
		"kr":"briye"
	},
	"id339":{
		"en":"shout",
		"kr":"kriye, kriy"
	},
	"id340":{
		"en":"show",
		"kr":"montre"
	},
	"id341":{
		"en":"shut",
		"kr":"ferme"
	},
	"id342":{
		"en":"sing",
		"kr":"sante, sant"
	},
	"id343":{
		"en":"sit",
		"kr":"asize, asiz"
	},
	"id344":{
		"en":"slap",
		"kr":"kalot"
	},
	"id345":{
		"en":"sleep",
		"kr":"dormi"
	},
	"id346":{
		"en":"slide",
		"kr":"glise, glis"
	},
	"id347":{
		"en":"smile",
		"kr":"sourir"
	},
	"id348":{
		"en":"sneeze",
		"kr":"terne"
	},
	"id349":{
		"en":"snif",
		"kr":"santi"
	},
	"id350":{
		"en":"solve",
		"kr":"rezoud"
	},
	"id351":{
		"en":"sow",
		"kr":"seme"
	},
	"id352":{
		"en":"sparkle",
		"kr":"briye or glase"
	},
	"id353":{
		"en":"speak",
		"kr":"koze, koz"
	},
	"id354":{
		"en":"specify",
		"kr":"spesifie"
	},
	"id355":{
		"en":"spell",
		"kr":"eple"
	},
	"id356":{
		"en":"spend",
		"kr":"depanse, depans"
	},
	"id357":{
		"en":"spit",
		"kr":"crase, cras"
	},
	"id358":{
		"en":"split",
		"kr":"fann"
	},
	"id359":{
		"en":"spoil",
		"kr":"gate, gat"
	},
	"id360":{
		"en":"spray",
		"kr":"spre"
	},
	"id361":{
		"en":"spread",
		"kr":"propaze, propaz"
	},
	"id362":{
		"en":"squat",
		"kr":"akroupi"
	},
	"id363":{
		"en":"stab",
		"kr":"pwagnarde, pwagnard"
	},
	"id364":{
		"en":"stand",
		"kr":"deboute, debout"
	},
	"id365":{
		"en":"start",
		"kr":"koumanse, koumans"
	},
	"id366":{
		"en":"stick",
		"kr":"kole, kol"
	},
	"id367":{
		"en":"stink",
		"kr":"santi pi"
	},
	"id368":{
		"en":"stir",
		"kr":"deleye, deley"
	},
	"id369":{
		"en":"stop",
		"kr":"arete, aret"
	},
	"id370":{
		"en":"straighten",
		"kr":"drese, dres or fer vin"
	},
	"id371":{
		"en":"drwat",
		"kr":""
	},
	"id372":{
		"en":"stroll",
		"kr":"mars-marse"
	},
	"id373":{
		"en":"submerge",
		"kr":"sibmerze"
	},
	"id374":{
		"en":"suck",
		"kr":"souse, sous"
	},
	"id375":{
		"en":"suggest",
		"kr":"sigzere, sigzer"
	},
	"id376":{
		"en":"surround",
		"kr":"antoure, antour"
	},
	"id377":{
		"en":"swallow",
		"kr":"avale, aval"
	},
	"id378":{
		"en":"sweat",
		"kr":"transpire, transpir"
	},
	"id379":{
		"en":"sweep",
		"kr":"balie"
	},
	"id380":{
		"en":"swim",
		"kr":"naze, naz"
	},
	"id381":{
		"en":"swing",
		"kr":"balanse, balans"
	},
	"id382":{
		"en":"take",
		"kr":"pran"
	},
	"id383":{
		"en":"taste",
		"kr":"goute, gout"
	},
	"id384":{
		"en":"teach",
		"kr":"ansegne, ansegn"
	},
	"id385":{
		"en":"tease",
		"kr":"sikane, sikann or takine,"
	},
	"id386":{
		"en":"takinn",
		"kr":""
	},
	"id387":{
		"en":"tell",
		"kr":"dir"
	},
	"id388":{
		"en":"test",
		"kr":"teste, test"
	},
	"id389":{
		"en":"thank",
		"kr":"remersie"
	},
	"id390":{
		"en":"think",
		"kr":"panse, pans"
	},
	"id391":{
		"en":"threaten",
		"kr":"menase, menas"
	},
	"id392":{
		"en":"throw",
		"kr":"avoye, avoy or lanse,"
	},
	"id393":{
		"en":"lans",
		"kr":""
	},
	"id394":{
		"en":"tick",
		"kr":"met enn rayt"
	},
	"id395":{
		"en":"tire",
		"kr":"fatige, fatig"
	},
	"id396":{
		"en":"tired",
		"kr":"touye, touy"
	},
	"id397":{
		"en":"touch",
		"kr":"touse, tous"
	},
	"id398":{
		"en":"translate",
		"kr":"tradir"
	},
	"id399":{
		"en":"transplant",
		"kr":"transplante, transplant"
	},
	"id400":{
		"en":"travel",
		"kr":"vwayaze, vwayaz"
	},
	"id401":{
		"en":"tremble",
		"kr":"tranble"
	},
	"id402":{
		"en":"trick",
		"kr":"trike"
	},
	"id403":{
		"en":"tumble",
		"kr":"tonbe, tom"
	},
	"id404":{
		"en":"turn",
		"kr":"tourne, tourn"
	},
	"id405":{
		"en":"uncover",
		"kr":"dekouver"
	},
	"id406":{
		"en":"understand",
		"kr":"konpran"
	},
	"id407":{
		"en":"unite",
		"kr":"inir"
	},
	"id408":{
		"en":"untie",
		"kr":"defer"
	},
	"id409":{
		"en":"use",
		"kr":"servi"
	},
	"id410":{
		"en":"utter",
		"kr":"prononse, pronons"
	},
	"id411":{
		"en":"verify",
		"kr":"verifie"
	},
	"id412":{
		"en":"vibrate",
		"kr":"vibre"
	},
	"id413":{
		"en":"visit",
		"kr":"vizite, vizit"
	},
	"id414":{
		"en":"vomit",
		"kr":"vomi"
	},
	"id415":{
		"en":"wait",
		"kr":"atann"
	},
	"id416":{
		"en":"wait",
		"kr":"espere, esper"
	},
	"id417":{
		"en":"wake",
		"kr":"leve, lev"
	},
	"id418":{
		"en":"walk",
		"kr":"marse, mars"
	},
	"id419":{
		"en":"wander",
		"kr":"chake"
	},
	"id420":{
		"en":"want",
		"kr":"anvi"
	},
	"id421":{
		"en":"warn",
		"kr":"averti"
	},
	"id422":{
		"en":"wash",
		"kr":"lave, lav"
	},
	"id423":{
		"en":"watch",
		"kr":"gete, get"
	},
	"id424":{
		"en":"wear",
		"kr":"mete, met"
	},
	"id425":{
		"en":"weep",
		"kr":"plore, plor"
	},
	"id426":{
		"en":"weigh",
		"kr":"mezire, mezir or peze,"
	},
	"id427":{
		"en":"pez",
		"kr":""
	},
	"id428":{
		"en":"welcome",
		"kr":"akeyir"
	},
	"id429":{
		"en":"whip",
		"kr":"fwete, fwet"
	},
	"id430":{
		"en":"whisper",
		"kr":"koz dousman or mirmire,"
	},
	"id431":{
		"en":"mirmir",
		"kr":""
	},
	"id432":{
		"en":"whistle",
		"kr":"sifle"
	},
	"id433":{
		"en":"win",
		"kr":"gagne, gagn"
	},
	"id434":{
		"en":"wipe",
		"kr":"souyer"
	},
	"id435":{
		"en":"withdraw",
		"kr":"tire, tir"
	},
	"id436":{
		"en":"work",
		"kr":"travay"
	},
	"id437":{
		"en":"wrap",
		"kr":"anbale, anbal"
	},
	"id438":{
		"en":"write",
		"kr":"ekrir"
	},
	"id439":{
		"en":"yawn",
		"kr":"baye"
	},
	"id440":{
		"en":"Numbers",
		"kr":"and counting"
	},
	"id441":{
		"en":"number",
		"kr":"nimero or nonb"
	},
	"id442":{
		"en":"one",
		"kr":"enn"
	},
	"id443":{
		"en":"two",
		"kr":"de"
	},
	"id444":{
		"en":"three",
		"kr":"trwa"
	},
	"id445":{
		"en":"four",
		"kr":"kat"
	},
	"id446":{
		"en":"five",
		"kr":"sink"
	},
	"id447":{
		"en":"six",
		"kr":"sis"
	},
	"id448":{
		"en":"seven",
		"kr":"set"
	},
	"id449":{
		"en":"eight",
		"kr":"wit"
	},
	"id450":{
		"en":"nine",
		"kr":"nef"
	},
	"id451":{
		"en":"ten",
		"kr":"dis"
	},
	"id452":{
		"en":"eleven",
		"kr":"onz"
	},
	"id453":{
		"en":"twelve",
		"kr":"douz"
	},
	"id454":{
		"en":"thirteen",
		"kr":"trez"
	},
	"id455":{
		"en":"fourteen",
		"kr":"katorz"
	},
	"id456":{
		"en":"fifteen",
		"kr":"kinz"
	},
	"id457":{
		"en":"sixteen",
		"kr":"sez"
	},
	"id458":{
		"en":"seventeen",
		"kr":"diset"
	},
	"id459":{
		"en":"eighteen",
		"kr":"dizwit"
	},
	"id460":{
		"en":"nineteen",
		"kr":"diznef"
	},
	"id461":{
		"en":"twenty",
		"kr":"vin"
	},
	"id462":{
		"en":"twenty",
		"kr":"one vint-e-enn"
	},
	"id463":{
		"en":"twenty",
		"kr":"two vennde"
	},
	"id464":{
		"en":"twenty",
		"kr":"three venntrwa"
	},
	"id465":{
		"en":"twenty",
		"kr":"four vennkat"
	},
	"id466":{
		"en":"twenty",
		"kr":"five vennsink"
	},
	"id467":{
		"en":"twenty",
		"kr":"six vennsis"
	},
	"id468":{
		"en":"twenty",
		"kr":"seven vennset"
	},
	"id469":{
		"en":"twenty",
		"kr":"eight vintwit"
	},
	"id470":{
		"en":"twenty",
		"kr":"nine vintnef"
	},
	"id471":{
		"en":"thirty",
		"kr":"trant"
	},
	"id472":{
		"en":"forty",
		"kr":"karannt"
	},
	"id473":{
		"en":"fifty",
		"kr":"sinkant"
	},
	"id474":{
		"en":"sixty",
		"kr":"swasant"
	},
	"id475":{
		"en":"seventy",
		"kr":"swasanntdis"
	},
	"id476":{
		"en":"eighty",
		"kr":"katrovin"
	},
	"id477":{
		"en":"ninety",
		"kr":"katrovin-dis"
	},
	"id478":{
		"en":"one",
		"kr":"hundred san"
	},
	"id479":{
		"en":"one",
		"kr":"thousand mil"
	},
	"id480":{
		"en":"one",
		"kr":"million enn milyon"
	},
	"id481":{
		"en":"first",
		"kr":"premie"
	},
	"id482":{
		"en":"second",
		"kr":"deziem"
	},
	"id483":{
		"en":"third",
		"kr":"trwaziem"
	},
	"id484":{
		"en":"fourth",
		"kr":"katiem"
	},
	"id485":{
		"en":"fifth",
		"kr":"sinkiem"
	},
	"id486":{
		"en":"sixth",
		"kr":"sisiem"
	},
	"id487":{
		"en":"seventh",
		"kr":"setiem"
	},
	"id488":{
		"en":"eighth",
		"kr":"witiem"
	},
	"id489":{
		"en":"ninth",
		"kr":"nefiem"
	},
	"id490":{
		"en":"tenth",
		"kr":"disiem"
	},
	"id491":{
		"en":"Quantities",
		"kr":""
	},
	"id492":{
		"en":"amount",
		"kr":"kantite"
	},
	"id493":{
		"en":"big",
		"kr":"gro"
	},
	"id494":{
		"en":"equal",
		"kr":"egal"
	},
	"id495":{
		"en":"even",
		"kr":"egal or regilie"
	},
	"id496":{
		"en":"how",
		"kr":" komie"
	},
	"id497":{
		"en":"much",
		"kr":"boukou"
	},
	"id498":{
		"en":"multiple",
		"kr":"miltip"
	},
	"id499":{
		"en":"numerous",
		"kr":"boukou"
	},
	"id500":{
		"en":"quantity",
		"kr":"kantite"
	},
	"id501":{
		"en":"quarter",
		"kr":"enn kar"
	},
	"id502":{
		"en":"rate",
		"kr":"tarif"
	},
	"id503":{
		"en":"size",
		"kr":"latay"
	},
	"id504":{
		"en":"small",
		"kr":"tipti"
	},
	"id505":{
		"en":"Time",
		"kr":"and date"
	},
	"id506":{
		"en":"Monday",
		"kr":"Lindi"
	},
	"id507":{
		"en":"Tuesday",
		"kr":"Mardi"
	},
	"id508":{
		"en":"Wednesday",
		"kr":"Merkredi"
	},
	"id509":{
		"en":"Thursday",
		"kr":"Zedi"
	},
	"id510":{
		"en":"Friday",
		"kr":"Vandredi"
	},
	"id511":{
		"en":"Saturday",
		"kr":"Samdi"
	},
	"id512":{
		"en":"Sunday",
		"kr":"Dimans"
	},
	"id513":{
		"en":"wikenn",
		"kr":"weekend"
	},
	"id514":{
		"en":"yesterday",
		"kr":"yer"
	},
	"id515":{
		"en":"January",
		"kr":"Zanvie"
	},
	"id516":{
		"en":"February",
		"kr":"Fevriye"
	},
	"id517":{
		"en":"March",
		"kr":"Mars"
	},
	"id518":{
		"en":"April",
		"kr":"Avril"
	},
	"id519":{
		"en":"May",
		"kr":"Me"
	},
	"id520":{
		"en":"June",
		"kr":"Zwin"
	},
	"id521":{
		"en":"July",
		"kr":"Zilie"
	},
	"id522":{
		"en":"August",
		"kr":"Out"
	},
	"id523":{
		"en":"September",
		"kr":"Septam"
	},
	"id524":{
		"en":"October",
		"kr":"Oktob"
	},
	"id525":{
		"en":"November",
		"kr":"Novam"
	},
	"id526":{
		"en":"December",
		"kr":"Desam"
	},
	"id527":{
		"en":"month",
		"kr":"mwa"
	},
	"id528":{
		"en":"monthly",
		"kr":"mansiel"
	},
	"id529":{
		"en":"afternoon",
		"kr":"lapremidi"
	},
	"id530":{
		"en":"afternoon",
		"kr":"tanto"
	},
	"id531":{
		"en":"anytime",
		"kr":"ninport kan"
	},
	"id532":{
		"en":"before",
		"kr":"avan"
	},
	"id533":{
		"en":"date",
		"kr":"dat"
	},
	"id534":{
		"en":"dawn",
		"kr":"lob"
	},
	"id535":{
		"en":"day",
		"kr":"zour"
	},
	"id536":{
		"en":"day",
		"kr":"lizour"
	},
	"id537":{
		"en":"early",
		"kr":"boner"
	},
	"id538":{
		"en":"evening",
		"kr":"aswar"
	},
	"id539":{
		"en":"immediately",
		"kr":"deswit or toutswit"
	},
	"id540":{
		"en":"later",
		"kr":"taler"
	},
	"id541":{
		"en":"long",
		"kr":"longtan"
	},
	"id542":{
		"en":"midnight",
		"kr":"minwi"
	},
	"id543":{
		"en":"minute",
		"kr":"minit"
	},
	"id544":{
		"en":"moment",
		"kr":"letan or moman"
	},
	"id545":{
		"en":"morning",
		"kr":"gramatin"
	},
	"id546":{
		"en":"night",
		"kr":"lanwit"
	},
	"id547":{
		"en":"noon",
		"kr":"midi"
	},
	"id548":{
		"en":"now",
		"kr":"aster-la"
	},
	"id549":{
		"en":"nowadays",
		"kr":"zordizour"
	},
	"id550":{
		"en":"often",
		"kr":"souvan"
	},
	"id551":{
		"en":"once",
		"kr":"enn sel fwa"
	},
	"id552":{
		"en":"recently",
		"kr":"fek or resaman"
	},
	"id553":{
		"en":"soon",
		"kr":"biento"
	},
	"id554":{
		"en":"time",
		"kr":"ler"
	},
	"id555":{
		"en":"today",
		"kr":"zordi"
	},
	"id556":{
		"en":"tomorrow",
		"kr":"demin or dime"
	},
	"id557":{
		"en":"week",
		"kr":"lasemenn"
	},
	"id558":{
		"en":"year",
		"kr":"lane"
	},
	"id559":{
		"en":"People",
		"kr":""
	},
	"id560":{
		"en":"anyone",
		"kr":"ninport ki sann-la"
	},
	"id561":{
		"en":"aunt",
		"kr":"matant"
	},
	"id562":{
		"en":"baby",
		"kr":"baba"
	},
	"id563":{
		"en":"boy",
		"kr":"garson"
	},
	"id564":{
		"en":"boyfriend",
		"kr":"kopin or pwinter"
	},
	"id565":{
		"en":"brother",
		"kr":"frer"
	},
	"id566":{
		"en":"brother",
		"kr":"in-law bofrer"
	},
	"id567":{
		"en":"child",
		"kr":"zenfan"
	},
	"id568":{
		"en":"childhood",
		"kr":"lafans"
	},
	"id569":{
		"en":"cousin",
		"kr":"kouzin"
	},
	"id570":{
		"en":"daughter",
		"kr":"tifi"
	},
	"id571":{
		"en":"daughter",
		"kr":"in-law belfi"
	},
	"id572":{
		"en":"father",
		"kr":"papa"
	},
	"id573":{
		"en":"father",
		"kr":"in-law boper"
	},
	"id574":{
		"en":"female",
		"kr":"femel"
	},
	"id575":{
		"en":"fisherman",
		"kr":"peser"
	},
	"id576":{
		"en":"girlfriend",
		"kr":"kopinn"
	},
	"id577":{
		"en":"grandchild",
		"kr":"ti-zanfan"
	},
	"id578":{
		"en":"grandfather",
		"kr":"granper"
	},
	"id579":{
		"en":"grandmother",
		"kr":"granmer"
	},
	"id580":{
		"en":"grandparents",
		"kr":"granparan"
	},
	"id581":{
		"en":"grandson",
		"kr":"ti-zanfan"
	},
	"id582":{
		"en":"husband",
		"kr":"mari or misie"
	},
	"id583":{
		"en":"lady",
		"kr":"madam"
	},
	"id584":{
		"en":"lady",
		"kr":"mamzel"
	},
	"id585":{
		"en":"male",
		"kr":"mal"
	},
	"id586":{
		"en":"man",
		"kr":"dimounn or zom"
	},
	"id587":{
		"en":"man",
		"kr":"zennzan"
	},
	"id588":{
		"en":"mister",
		"kr":"misie"
	},
	"id589":{
		"en":"mother",
		"kr":"mama"
	},
	"id590":{
		"en":"mother",
		"kr":"in-law belmer"
	},
	"id591":{
		"en":"nephew",
		"kr":"neve"
	},
	"id592":{
		"en":"niece",
		"kr":"nies"
	},
	"id593":{
		"en":"nobody",
		"kr":"personn"
	},
	"id594":{
		"en":"nurse",
		"kr":"ners"
	},
	"id595":{
		"en":"people",
		"kr":"dimounn"
	},
	"id596":{
		"en":"person",
		"kr":"dimounn"
	},
	"id597":{
		"en":"relative",
		"kr":"fami"
	},
	"id598":{
		"en":"sister",
		"kr":"ser"
	},
	"id599":{
		"en":"sister",
		"kr":"in-law belser"
	},
	"id600":{
		"en":"son",
		"kr":"garson"
	},
	"id601":{
		"en":"son",
		"kr":"in-law zann"
	},
	"id602":{
		"en":"teenager",
		"kr":"adolesan"
	},
	"id603":{
		"en":"teens",
		"kr":"ladolesans"
	},
	"id604":{
		"en":"uncle",
		"kr":"tonton"
	},
	"id605":{
		"en":"wife",
		"kr":"fam"
	},
	"id606":{
		"en":"woman",
		"kr":"fam"
	},
	"id607":{
		"en":"Natural",
		"kr":"world"
	},
	"id608":{
		"en":"animal",
		"kr":"zanimo"
	},
	"id609":{
		"en":"bird",
		"kr":"zwazo"
	},
	"id610":{
		"en":"bull",
		"kr":"toro"
	},
	"id611":{
		"en":"cat",
		"kr":"sat"
	},
	"id612":{
		"en":"chicken",
		"kr":"poul"
	},
	"id613":{
		"en":"cow",
		"kr":"vas"
	},
	"id614":{
		"en":"dog",
		"kr":"lisien"
	},
	"id615":{
		"en":"duck",
		"kr":"kanar"
	},
	"id616":{
		"en":"elephant",
		"kr":"lelefan"
	},
	"id617":{
		"en":"fish",
		"kr":"pwason"
	},
	"id618":{
		"en":"frog",
		"kr":"grenouy"
	},
	"id619":{
		"en":"goat",
		"kr":"kabri"
	},
	"id620":{
		"en":"mammal",
		"kr":"mamifer"
	},
	"id621":{
		"en":"monkey",
		"kr":"zako"
	},
	"id622":{
		"en":"mouse",
		"kr":"souri"
	},
	"id623":{
		"en":"pig",
		"kr":"koson"
	},
	"id624":{
		"en":"rabbit",
		"kr":"lapin"
	},
	"id625":{
		"en":"rat",
		"kr":"lera"
	},
	"id626":{
		"en":"shark",
		"kr":"rekin"
	},
	"id627":{
		"en":"snake",
		"kr":"serpan"
	},
	"id628":{
		"en":"tortoise",
		"kr":"torti"
	},
	"id629":{
		"en":"whale",
		"kr":"labalenn"
	},
	"id630":{
		"en":"ant",
		"kr":"fourmi"
	},
	"id631":{
		"en":"bee",
		"kr":"mous-dimiel"
	},
	"id632":{
		"en":"butterfly",
		"kr":"papiyon"
	},
	"id633":{
		"en":"centipede",
		"kr":"sanpie"
	},
	"id634":{
		"en":"insect",
		"kr":"bebet"
	},
	"id635":{
		"en":"ladybird",
		"kr":"poulbondie"
	},
	"id636":{
		"en":"mosquito",
		"kr":"moustik"
	},
	"id637":{
		"en":"snail",
		"kr":"kourpa"
	},
	"id638":{
		"en":"spider",
		"kr":"laregne"
	},
	"id639":{
		"en":"worm",
		"kr":"lever"
	},
	"id640":{
		"en":"branch",
		"kr":"brans"
	},
	"id641":{
		"en":"bush",
		"kr":"bwison"
	},
	"id642":{
		"en":"grass",
		"kr":"lerb"
	},
	"id643":{
		"en":"plant",
		"kr":"plant"
	},
	"id644":{
		"en":"tree",
		"kr":"pie"
	},
	"id645":{
		"en":"weed",
		"kr":"move lerb"
	},
	"id646":{
		"en":"summer",
		"kr":"lete"
	},
	"id647":{
		"en":"winter",
		"kr":"liver"
	},
	"id648":{
		"en":"breeze",
		"kr":"labriz"
	},
	"id649":{
		"en":"cloud",
		"kr":"niaz"
	},
	"id650":{
		"en":"cyclone",
		"kr":"siklonn"
	},
	"id651":{
		"en":"dew",
		"kr":"laroze"
	},
	"id652":{
		"en":"rain",
		"kr":"lapli"
	},
	"id653":{
		"en":"rainy",
		"kr":"lapli / lapli"
	},
	"id654":{
		"en":"snow",
		"kr":"lanez"
	},
	"id655":{
		"en":"storm",
		"kr":"tanpet"
	},
	"id656":{
		"en":"thunderstorm",
		"kr":"loraz"
	},
	"id657":{
		"en":"weather",
		"kr":"klima"
	},
	"id658":{
		"en":"wind",
		"kr":"divan"
	},
	"id659":{
		"en":"coral",
		"kr":"koray"
	},
	"id660":{
		"en":"earth",
		"kr":"later"
	},
	"id661":{
		"en":"gravity",
		"kr":"gravite"
	},
	"id662":{
		"en":"moon",
		"kr":"lalinn"
	},
	"id663":{
		"en":"moon",
		"kr":"plenn linn"
	},
	"id664":{
		"en":"nature",
		"kr":"lanatir"
	},
	"id665":{
		"en":"ocean",
		"kr":"losean"
	},
	"id666":{
		"en":"sky",
		"kr":"lesiel"
	},
	"id667":{
		"en":"sun",
		"kr":"soley"
	},
	"id668":{
		"en":"universe",
		"kr":"liniver"
	},
	"id669":{
		"en":"world",
		"kr":"lemond"
	},
	"id670":{
		"en":"worldwide",
		"kr":"mondial"
	},
	"id671":{
		"en":"The",
		"kr":"body"
	},
	"id672":{
		"en":"abdomen",
		"kr":"abdomenn"
	},
	"id673":{
		"en":"ankle",
		"kr":"sevi"
	},
	"id674":{
		"en":"arm",
		"kr":"lebra"
	},
	"id675":{
		"en":"blood",
		"kr":"disan"
	},
	"id676":{
		"en":"body",
		"kr":"lecor"
	},
	"id677":{
		"en":"bone",
		"kr":"lezo"
	},
	"id678":{
		"en":"brain",
		"kr":"laservel or servo"
	},
	"id679":{
		"en":"breath",
		"kr":"lesouf"
	},
	"id680":{
		"en":"cheek",
		"kr":"lazou"
	},
	"id681":{
		"en":"chest",
		"kr":"torax or tors"
	},
	"id682":{
		"en":"chin",
		"kr":"manton"
	},
	"id683":{
		"en":"disease",
		"kr":"maladi"
	},
	"id684":{
		"en":"dizziness",
		"kr":"vertiz"
	},
	"id685":{
		"en":"dizzy",
		"kr":"tourdi"
	},
	"id686":{
		"en":"ear",
		"kr":"zorey"
	},
	"id687":{
		"en":"elbow",
		"kr":"koud"
	},
	"id688":{
		"en":"eye",
		"kr":"lizie"
	},
	"id689":{
		"en":"eyebrow",
		"kr":"soursi"
	},
	"id690":{
		"en":"eyelash",
		"kr":"sil"
	},
	"id691":{
		"en":"eyelid",
		"kr":"popier"
	},
	"id692":{
		"en":"feet",
		"kr":"lipie"
	},
	"id693":{
		"en":"finger",
		"kr":"ledwa"
	},
	"id694":{
		"en":"gut",
		"kr":"lintestin"
	},
	"id695":{
		"en":"hair",
		"kr":"seve"
	},
	"id696":{
		"en":"hammer",
		"kr":"marto"
	},
	"id697":{
		"en":"hand",
		"kr":"lame"
	},
	"id698":{
		"en":"head",
		"kr":"latet"
	},
	"id699":{
		"en":"heart",
		"kr":"leker"
	},
	"id700":{
		"en":"intestine",
		"kr":"lintestin"
	},
	"id701":{
		"en":"jaw",
		"kr":"lamaswar"
	},
	"id702":{
		"en":"kidney",
		"kr":"lerin"
	},
	"id703":{
		"en":"knee",
		"kr":"zenou"
	},
	"id704":{
		"en":"lips",
		"kr":"lalev"
	},
	"id705":{
		"en":"liver",
		"kr":"lefwa"
	},
	"id706":{
		"en":"lung",
		"kr":"poumon"
	},
	"id707":{
		"en":"mind",
		"kr":"lespri"
	},
	"id708":{
		"en":"moustache",
		"kr":"moustas"
	},
	"id709":{
		"en":"mouth",
		"kr":"labous"
	},
	"id710":{
		"en":"muscle",
		"kr":"misk"
	},
	"id711":{
		"en":"neck",
		"kr":"licou"
	},
	"id712":{
		"en":"nerve",
		"kr":"ner"
	},
	"id713":{
		"en":"nose",
		"kr":"nene"
	},
	"id714":{
		"en":"shoulder",
		"kr":"zepol"
	},
	"id715":{
		"en":"skeleton",
		"kr":"skelet"
	},
	"id716":{
		"en":"skin",
		"kr":"lapo"
	},
	"id717":{
		"en":"stomach",
		"kr":"lestoma"
	},
	"id718":{
		"en":"tendon",
		"kr":"tandon"
	},
	"id719":{
		"en":"thigh",
		"kr":"lakwis"
	},
	"id720":{
		"en":"throat",
		"kr":"lagorz"
	},
	"id721":{
		"en":"thumb",
		"kr":"pous"
	},
	"id722":{
		"en":"toe",
		"kr":"ledwa lipie"
	},
	"id723":{
		"en":"tongue",
		"kr":"lalang"
	},
	"id724":{
		"en":"tooth",
		"kr":"ledan"
	},
	"id725":{
		"en":"vein",
		"kr":"lavenn"
	},
	"id726":{
		"en":"voice",
		"kr":"lavwa"
	},
	"id727":{
		"en":"waist",
		"kr":"latay"
	},
	"id728":{
		"en":"wrist",
		"kr":"pwagne"
	},
	"id729":{
		"en":"Around",
		"kr":"the house"
	},
	"id730":{
		"en":"bathroom",
		"kr":"sal-debin"
	},
	"id731":{
		"en":"bed",
		"kr":"sheets dra"
	},
	"id732":{
		"en":"bedroom",
		"kr":"lasam"
	},
	"id733":{
		"en":"kitchen",
		"kr":"lakwizinn"
	},
	"id734":{
		"en":"roof",
		"kr":"twa"
	},
	"id735":{
		"en":"room",
		"kr":"lasam"
	},
	"id736":{
		"en":"sitting",
		"kr":"room salon"
	},
	"id737":{
		"en":"toilet",
		"kr":"twalet"
	},
	"id738":{
		"en":"wall",
		"kr":"miray"
	},
	"id739":{
		"en":"wash",
		"kr":"room twalet"
	},
	"id740":{
		"en":"window",
		"kr":"lafnet"
	},
	"id741":{
		"en":"yard",
		"kr":"courtyard lakour"
	},
	"id742":{
		"en":"basket",
		"kr":"panie"
	},
	"id743":{
		"en":"bath",
		"kr":"bin"
	},
	"id744":{
		"en":"bed",
		"kr":"lili"
	},
	"id745":{
		"en":"bin",
		"kr":"poubel"
	},
	"id746":{
		"en":"binoculars",
		"kr":"zimel"
	},
	"id747":{
		"en":"blanket",
		"kr":"molton"
	},
	"id748":{
		"en":"book",
		"kr":"liv"
	},
	"id749":{
		"en":"bottle",
		"kr":"boutey"
	},
	"id750":{
		"en":"bowl",
		"kr":"bol"
	},
	"id751":{
		"en":"box",
		"kr":"bwat"
	},
	"id752":{
		"en":"bucket",
		"kr":"seo"
	},
	"id753":{
		"en":"bulb",
		"kr":"glob"
	},
	"id754":{
		"en":"chair",
		"kr":"sez"
	},
	"id755":{
		"en":"clock",
		"kr":"revey"
	},
	"id756":{
		"en":"cushion",
		"kr":"kousin"
	},
	"id757":{
		"en":"door",
		"kr":"laport"
	},
	"id758":{
		"en":"drain",
		"kr":"drin"
	},
	"id759":{
		"en":"drawer",
		"kr":"tirwar"
	},
	"id760":{
		"en":"envelope",
		"kr":"lanvlop"
	},
	"id761":{
		"en":"glass",
		"kr":"ver"
	},
	"id762":{
		"en":"glasses",
		"kr":"spectacles linet"
	},
	"id763":{
		"en":"handle",
		"kr":"pwagne"
	},
	"id764":{
		"en":"key",
		"kr":"lakle"
	},
	"id765":{
		"en":"knife",
		"kr":"kouto"
	},
	"id766":{
		"en":"mirror",
		"kr":"laglas or mirwar"
	},
	"id767":{
		"en":"oven",
		"kr":"four"
	},
	"id768":{
		"en":"pane",
		"kr":"karo vit"
	},
	"id769":{
		"en":"pillow",
		"kr":"lorye"
	},
	"id770":{
		"en":"pin",
		"kr":"pinn"
	},
	"id771":{
		"en":"pin",
		"kr":"zepeng"
	},
	"id772":{
		"en":"plug",
		"kr":"pleg"
	},
	"id773":{
		"en":"pool",
		"kr":"pisinn"
	},
	"id774":{
		"en":"pot",
		"kr":"vaz"
	},
	"id775":{
		"en":"purse",
		"kr":"portmone"
	},
	"id776":{
		"en":"refrigerator",
		"kr":"frizider"
	},
	"id777":{
		"en":"scissors",
		"kr":"sizo"
	},
	"id778":{
		"en":"screw",
		"kr":"vis"
	},
	"id779":{
		"en":"screwdriver",
		"kr":"tournavis"
	},
	"id780":{
		"en":"shower",
		"kr":"dous"
	},
	"id781":{
		"en":"sink",
		"kr":"levie"
	},
	"id782":{
		"en":"spade",
		"kr":"lapel"
	},
	"id783":{
		"en":"spoon",
		"kr":"kouyer"
	},
	"id784":{
		"en":"stairs",
		"kr":"leskalie"
	},
	"id785":{
		"en":"suitcase",
		"kr":"valiz"
	},
	"id786":{
		"en":"table",
		"kr":"latab"
	},
	"id787":{
		"en":"telephone",
		"kr":"telefonn"
	},
	"id788":{
		"en":"television",
		"kr":"televizion"
	},
	"id789":{
		"en":"toilet",
		"kr":"twalet"
	},
	"id790":{
		"en":"towel",
		"kr":"serviet"
	},
	"id791":{
		"en":"tweezers",
		"kr":"pins"
	},
	"id792":{
		"en":"umbrella",
		"kr":"parasol"
	},
	"id793":{
		"en":"wardrobe",
		"kr":"larmwar"
	},
	"id794":{
		"en":"wash",
		"kr":"basin lavabo"
	},
	"id795":{
		"en":"watch",
		"kr":"mont"
	},
	"id796":{
		"en":"wire",
		"kr":"difil"
	},
	"id797":{
		"en":"Food",
		"kr":"and drink"
	},
	"id798":{
		"en":"bread",
		"kr":"dipin"
	},
	"id799":{
		"en":"cake",
		"kr":"gato"
	},
	"id800":{
		"en":"cheese",
		"kr":"fromaz"
	},
	"id801":{
		"en":"dessert",
		"kr":"deser"
	},
	"id802":{
		"en":"egg",
		"kr":"dizef"
	},
	"id803":{
		"en":"olive",
		"kr":"zoliv"
	},
	"id804":{
		"en":"omelette",
		"kr":"omlet"
	},
	"id805":{
		"en":"onion",
		"kr":"zwayon"
	},
	"id806":{
		"en":"pepper",
		"kr":"dipwav"
	},
	"id807":{
		"en":"potato",
		"kr":"pomdeter"
	},
	"id808":{
		"en":"rice",
		"kr":"diri"
	},
	"id809":{
		"en":"soup",
		"kr":"lasoup"
	},
	"id810":{
		"en":"tomato",
		"kr":"tomat"
	},
	"id811":{
		"en":"vanilla",
		"kr":"lavani"
	},
	"id812":{
		"en":"apple",
		"kr":"pom"
	},
	"id813":{
		"en":"banana",
		"kr":"banann"
	},
	"id814":{
		"en":"grape",
		"kr":"rezin"
	},
	"id815":{
		"en":"melon",
		"kr":"melon"
	},
	"id816":{
		"en":"orange",
		"kr":"zoranz"
	},
	"id817":{
		"en":"peach",
		"kr":"pes"
	},
	"id818":{
		"en":"pineapple",
		"kr":"zanana"
	},
	"id819":{
		"en":"watermelon",
		"kr":"melondo"
	},
	"id820":{
		"en":"beer",
		"kr":"labier"
	},
	"id821":{
		"en":"coffee",
		"kr":"kafe"
	},
	"id822":{
		"en":"juice",
		"kr":"zi"
	},
	"id823":{
		"en":"milk",
		"kr":"dile"
	},
	"id824":{
		"en":"tea",
		"kr":"dite"
	},
	"id825":{
		"en":"water",
		"kr":"delo"
	},
	"id826":{
		"en":"wine",
		"kr":"divin"
	},
	"id827":{
		"en":"Clothes",
		"kr":""
	},
	"id828":{
		"en":"belt",
		"kr":"sintir"
	},
	"id829":{
		"en":"button",
		"kr":"bouton"
	},
	"id830":{
		"en":"coat",
		"kr":"palto"
	},
	"id831":{
		"en":"dress",
		"kr":"rob"
	},
	"id832":{
		"en":"glove",
		"kr":"legan"
	},
	"id833":{
		"en":"pocket",
		"kr":"poz"
	},
	"id834":{
		"en":"pyjamas",
		"kr":"pizama"
	},
	"id835":{
		"en":"shirt",
		"kr":"semiz"
	},
	"id836":{
		"en":"shoe",
		"kr":"soulie"
	},
	"id837":{
		"en":"skirt",
		"kr":"zip"
	},
	"id838":{
		"en":"sock",
		"kr":"soset"
	},
	"id839":{
		"en":"sweater",
		"kr":"poulover or triko"
	},
	"id840":{
		"en":"trousers",
		"kr":"pantalon"
	},
	"id841":{
		"en":"Colours",
		"kr":""
	},
	"id842":{
		"en":"colour",
		"kr":"kouler"
	},
	"id843":{
		"en":"black",
		"kr":"nwar"
	},
	"id844":{
		"en":"blue",
		"kr":"ble"
	},
	"id845":{
		"en":"brown",
		"kr":"maron"
	},
	"id846":{
		"en":"green",
		"kr":"ver"
	},
	"id847":{
		"en":"grey",
		"kr":"gri"
	},
	"id848":{
		"en":"orange",
		"kr":"zoranz"
	},
	"id849":{
		"en":"pink",
		"kr":"roz"
	},
	"id850":{
		"en":"purple",
		"kr":"violet"
	},
	"id851":{
		"en":"red",
		"kr":"rouz"
	},
	"id852":{
		"en":"white",
		"kr":"blan"
	},
	"id853":{
		"en":"yellow",
		"kr":"zonn"
	},
	"id854":{
		"en":"Finding",
		"kr":"your way"
	},
	"id855":{
		"en":"left",
		"kr":"gos"
	},
	"id856":{
		"en":"near",
		"kr":"pre"
	},
	"id857":{
		"en":"north",
		"kr":"lenor"
	},
	"id858":{
		"en":"outdoor",
		"kr":"an-plener"
	},
	"id859":{
		"en":"outside",
		"kr":"deor"
	},
	"id860":{
		"en":"right",
		"kr":"drwat"
	},
	"id861":{
		"en":"south",
		"kr":"lesid"
	},
	"id862":{
		"en":"there",
		"kr":"la"
	},
	"id863":{
		"en":"underneath",
		"kr":"anba"
	},
	"id864":{
		"en":"west",
		"kr":"lwes"
	},
	"id865":{
		"en":"Places",
		"kr":""
	},
	"id866":{
		"en":"gate",
		"kr":"lantre"
	},
	"id867":{
		"en":"ground",
		"kr":"later"
	},
	"id868":{
		"en":"hospital",
		"kr":"lopital"
	},
	"id869":{
		"en":"market",
		"kr":"bazar"
	},
	"id870":{
		"en":"mountain",
		"kr":"montagn"
	},
	"id871":{
		"en":"over",
		"kr":"lor"
	},
	"id872":{
		"en":"overseas",
		"kr":"lot pei"
	},
	"id873":{
		"en":"place",
		"kr":"plas"
	},
	"id874":{
		"en":"sea",
		"kr":"lamer"
	},
	"id875":{
		"en":"space",
		"kr":"lespas"
	},
	"id876":{
		"en":"town",
		"kr":"lavil"
	},
	"id877":{
		"en":"village",
		"kr":"vilaz"
	},
	"id878":{
		"en":"Measurements",
		"kr":""
	},
	"id879":{
		"en":"centimetre",
		"kr":"santimet"
	},
	"id880":{
		"en":"foot",
		"kr":"pie"
	},
	"id881":{
		"en":"inch",
		"kr":"pous"
	},
	"id882":{
		"en":"kilometre",
		"kr":"kilomet"
	},
	"id883":{
		"en":"metre",
		"kr":"met"
	},
	"id884":{
		"en":"mile",
		"kr":"mil"
	},
	"id885":{
		"en":"millimetre",
		"kr":"milimet"
	},
	"id886":{
		"en":"Other",
		"kr":"general vocabulary"
	},
	"id887":{
		"en":"ability",
		"kr":"kapasite"
	},
	"id888":{
		"en":"absence",
		"kr":"absans or labsans"
	},
	"id889":{
		"en":"absent",
		"kr":"absan"
	},
	"id890":{
		"en":"absolutely",
		"kr":"absoliman"
	},
	"id891":{
		"en":"accident",
		"kr":"aksidan"
	},
	"id892":{
		"en":"advantage",
		"kr":"lavantaz"
	},
	"id893":{
		"en":"advice",
		"kr":"konsey"
	},
	"id894":{
		"en":"agree",
		"kr":"dakor"
	},
	"id895":{
		"en":"agreement",
		"kr":"lakor"
	},
	"id896":{
		"en":"air",
		"kr":"ler"
	},
	"id897":{
		"en":"alcohol",
		"kr":"lalkol"
	},
	"id898":{
		"en":"alike",
		"kr":"parey"
	},
	"id899":{
		"en":"all",
		"kr":"tou"
	},
	"id900":{
		"en":"alone",
		"kr":"tousel"
	},
	"id901":{
		"en":"already",
		"kr":"deza"
	},
	"id902":{
		"en":"always",
		"kr":"touzour"
	},
	"id903":{
		"en":"amazement",
		"kr":"etonnman"
	},
	"id904":{
		"en":"amusement",
		"kr":"lamizman"
	},
	"id905":{
		"en":"angle",
		"kr":"lang"
	},
	"id906":{
		"en":"angry",
		"kr":"ankoler"
	},
	"id907":{
		"en":"answer",
		"kr":"repons"
	},
	"id908":{
		"en":"anything",
		"kr":"ninport ki zafer"
	},
	"id909":{
		"en":"appointment",
		"kr":"randevou"
	},
	"id910":{
		"en":"approval",
		"kr":"lakor"
	},
	"id911":{
		"en":"bad",
		"kr":"move"
	},
	"id912":{
		"en":"bag",
		"kr":"sak"
	},
	"id913":{
		"en":"balance",
		"kr":"balans"
	},
	"id914":{
		"en":"basin",
		"kr":"kivet"
	},
	"id915":{
		"en":"beautiful",
		"kr":"zoli"
	},
	"id916":{
		"en":"because",
		"kr":"akoz or parski"
	},
	"id917":{
		"en":"behaviour",
		"kr":"konportman"
	},
	"id918":{
		"en":"belief",
		"kr":"krwayans"
	},
	"id919":{
		"en":"bend",
		"kr":"kontour"
	},
	"id920":{
		"en":"benefit",
		"kr":"lavantaz"
	},
	"id921":{
		"en":"better",
		"kr":"meyer"
	},
	"id922":{
		"en":"bicycle",
		"kr":"bisiklet"
	},
	"id923":{
		"en":"birth",
		"kr":"nesans"
	},
	"id924":{
		"en":"blame",
		"kr":"blam"
	},
	"id925":{
		"en":"blind",
		"kr":"aveg"
	},
	"id926":{
		"en":"blindness",
		"kr":"avegleman"
	},
	"id927":{
		"en":"blow",
		"kr":"kou"
	},
	"id928":{
		"en":"blur",
		"kr":"flou"
	},
	"id929":{
		"en":"boat",
		"kr":"bato"
	},
	"id930":{
		"en":"boss",
		"kr":"patron"
	},
	"id931":{
		"en":"brick",
		"kr":"blok"
	},
	"id932":{
		"en":"bridge",
		"kr":"pon"
	},
	"id933":{
		"en":"bright",
		"kr":"vif"
	},
	"id934":{
		"en":"brush",
		"kr":"bros"
	},
	"id935":{
		"en":"burst",
		"kr":"eklatman"
	},
	"id936":{
		"en":"business",
		"kr":"bizness"
	},
	"id937":{
		"en":"but",
		"kr":"me"
	},
	"id938":{
		"en":"cane",
		"kr":"kann"
	},
	"id939":{
		"en":"cap",
		"kr":"kap or kasket"
	},
	"id940":{
		"en":"card",
		"kr":"kart"
	},
	"id941":{
		"en":"careful",
		"kr":"fer attension"
	},
	"id942":{
		"en":"careless",
		"kr":"foupamal"
	},
	"id943":{
		"en":"cast",
		"kr":"kast"
	},
	"id944":{
		"en":"castle",
		"kr":"sato"
	},
	"id945":{
		"en":"caution",
		"kr":"prekosion"
	},
	"id946":{
		"en":"cautious",
		"kr":"pridan"
	},
	"id947":{
		"en":"cave",
		"kr":"lakav"
	},
	"id948":{
		"en":"celebration",
		"kr":"selebrasion"
	},
	"id949":{
		"en":"centre",
		"kr":"sant"
	},
	"id950":{
		"en":"chain",
		"kr":"lasenn"
	},
	"id951":{
		"en":"chalk",
		"kr":"lakre"
	},
	"id952":{
		"en":"chance",
		"kr":"sans"
	},
	"id953":{
		"en":"charm",
		"kr":"sarm"
	},
	"id954":{
		"en":"chase",
		"kr":"lasas"
	},
	"id955":{
		"en":"cheap",
		"kr":"bomarse"
	},
	"id956":{
		"en":"cheater",
		"kr":"voler"
	},
	"id957":{
		"en":"chemical",
		"kr":"simik"
	},
	"id958":{
		"en":"choice",
		"kr":"swa"
	},
	"id959":{
		"en":"church",
		"kr":"legliz"
	},
	"id960":{
		"en":"circle",
		"kr":"serk"
	},
	"id961":{
		"en":"city",
		"kr":"site"
	},
	"id962":{
		"en":"claim",
		"kr":"reklamation"
	},
	"id963":{
		"en":"clean",
		"kr":"prop"
	},
	"id964":{
		"en":"clear",
		"kr":"kler"
	},
	"id965":{
		"en":"climate",
		"kr":"klima"
	},
	"id966":{
		"en":"close",
		"kr":"proz avec"
	},
	"id967":{
		"en":"cloth",
		"kr":"latwal"
	},
	"id968":{
		"en":"clumsy",
		"kr":"maladrwa"
	},
	"id969":{
		"en":"cold",
		"kr":"fre"
	},
	"id970":{
		"en":"cold",
		"kr":"lagrip"
	},
	"id971":{
		"en":"complaint",
		"kr":"konplint"
	},
	"id972":{
		"en":"completely",
		"kr":"konpletman"
	},
	"id973":{
		"en":"confuse",
		"kr":"konfizion"
	},
	"id974":{
		"en":"connection",
		"kr":"koneksion"
	},
	"id975":{
		"en":"conscious",
		"kr":"konsian"
	},
	"id976":{
		"en":"cook",
		"kr":"kwizinie"
	},
	"id977":{
		"en":"cord",
		"kr":"lakord"
	},
	"id978":{
		"en":"correct",
		"kr":"exakt"
	},
	"id979":{
		"en":"correction",
		"kr":"koreksion"
	},
	"id980":{
		"en":"couple",
		"kr":"koup"
	},
	"id981":{
		"en":"cover",
		"kr":"kouvertir"
	},
	"id982":{
		"en":"crazy",
		"kr":"fou"
	},
	"id983":{
		"en":"creation",
		"kr":"kreasion"
	},
	"id984":{
		"en":"credit",
		"kr":"kredi or merit"
	},
	"id985":{
		"en":"crime",
		"kr":"krim"
	},
	"id986":{
		"en":"crowd",
		"kr":"lafoul"
	},
	"id987":{
		"en":"cruel",
		"kr":"kriel"
	},
	"id988":{
		"en":"cup",
		"kr":"tas"
	},
	"id989":{
		"en":"current",
		"kr":"kouran"
	},
	"id990":{
		"en":"curve",
		"kr":"kontour"
	},
	"id991":{
		"en":"damage",
		"kr":"domaz"
	},
	"id992":{
		"en":"damp",
		"kr":"mwat or imid"
	},
	"id993":{
		"en":"dance",
		"kr":"dans"
	},
	"id994":{
		"en":"danger",
		"kr":"danze"
	},
	"id995":{
		"en":"dangerous",
		"kr":"danzere"
	},
	"id996":{
		"en":"dark",
		"kr":"nwar"
	},
	"id997":{
		"en":"dead",
		"kr":"mor"
	},
	"id998":{
		"en":"deaf",
		"kr":"sourd"
	},
	"id999":{
		"en":"death",
		"kr":"lamor"
	},
	"id1000":{
		"en":"debt",
		"kr":"det"
	},
	"id1001":{
		"en":"decision",
		"kr":"desizion"
	},
	"id1002":{
		"en":"decoration",
		"kr":"dekorasion"
	},
	"id1003":{
		"en":"decorative",
		"kr":"dekoratif"
	},
	"id1004":{
		"en":"deeply",
		"kr":"profondeman"
	},
	"id1005":{
		"en":"defence",
		"kr":"defans"
	},
	"id1006":{
		"en":"defensive",
		"kr":"defansi"
	},
	"id1007":{
		"en":"degree",
		"kr":"degre"
	},
	"id1008":{
		"en":"deliberately",
		"kr":"expreseman"
	},
	"id1009":{
		"en":"delicate",
		"kr":"frazil"
	},
	"id1010":{
		"en":"delicious",
		"kr":"bon"
	},
	"id1011":{
		"en":"delivery",
		"kr":"livrezon"
	},
	"id1012":{
		"en":"demonstration",
		"kr":"demonstrasion"
	},
	"id1013":{
		"en":"dependency",
		"kr":"depandans"
	},
	"id1014":{
		"en":"dependent",
		"kr":"depandan"
	},
	"id1015":{
		"en":"deposit",
		"kr":"depo or depozit"
	},
	"id1016":{
		"en":"desire",
		"kr":"dezir"
	},
	"id1017":{
		"en":"detail",
		"kr":"detay"
	},
	"id1018":{
		"en":"development",
		"kr":"devlopman"
	},
	"id1019":{
		"en":"difference",
		"kr":"diferans"
	},
	"id1020":{
		"en":"different",
		"kr":"diferan"
	},
	"id1021":{
		"en":"difficult",
		"kr":"difisil"
	},
	"id1022":{
		"en":"difficulty",
		"kr":"difikilte"
	},
	"id1023":{
		"en":"direct",
		"kr":"direk"
	},
	"id1024":{
		"en":"directly",
		"kr":"direkteman"
	},
	"id1025":{
		"en":"dirt",
		"kr":"salte"
	},
	"id1026":{
		"en":"dirty",
		"kr":"sal"
	},
	"id1027":{
		"en":"disadvantage",
		"kr":"dezavantaz"
	},
	"id1028":{
		"en":"discovery",
		"kr":"dekouver or trouvay"
	},
	"id1029":{
		"en":"discussion",
		"kr":"diskision"
	},
	"id1030":{
		"en":"disorder",
		"kr":"dezord"
	},
	"id1031":{
		"en":"disorderly",
		"kr":"an dezord"
	},
	"id1032":{
		"en":"distance",
		"kr":"distans"
	},
	"id1033":{
		"en":"distant",
		"kr":"distan or lwin"
	},
	"id1034":{
		"en":"distribution",
		"kr":"distribision"
	},
	"id1035":{
		"en":"doctor",
		"kr":"dokter"
	},
	"id1036":{
		"en":"doubt",
		"kr":"dout"
	},
	"id1037":{
		"en":"drawing",
		"kr":"desin"
	},
	"id1038":{
		"en":"dream",
		"kr":"rev"
	},
	"id1039":{
		"en":"drink",
		"kr":"bwason"
	},
	"id1040":{
		"en":"drop",
		"kr":"gout"
	},
	"id1041":{
		"en":"dry",
		"kr":"sek"
	},
	"id1042":{
		"en":"duplicate",
		"kr":"kopi"
	},
	"id1043":{
		"en":"each",
		"kr":"sak"
	},
	"id1044":{
		"en":"easily",
		"kr":"fasilman"
	},
	"id1045":{
		"en":"easy",
		"kr":"fasil"
	},
	"id1046":{
		"en":"economical",
		"kr":"ekonomik"
	},
	"id1047":{
		"en":"economy",
		"kr":"lekonomi"
	},
	"id1048":{
		"en":"edge",
		"kr":"bor or rebor"
	},
	"id1049":{
		"en":"education",
		"kr":"ledikasion"
	},
	"id1050":{
		"en":"effect",
		"kr":"lefe"
	},
	"id1051":{
		"en":"effective",
		"kr":"efektif"
	},
	"id1052":{
		"en":"effectiveness",
		"kr":"lefikasite"
	},
	"id1053":{
		"en":"electric",
		"kr":"elektrik"
	},
	"id1054":{
		"en":"electrician",
		"kr":"elektrisien"
	},
	"id1055":{
		"en":"electricity",
		"kr":"kouran"
	},
	"id1056":{
		"en":"embarrassment",
		"kr":"lanbara"
	},
	"id1057":{
		"en":"encouragement",
		"kr":"lankourazman"
	},
	"id1058":{
		"en":"end",
		"kr":"lafin"
	},
	"id1059":{
		"en":"engine",
		"kr":"moter"
	},
	"id1060":{
		"en":"English",
		"kr":"Angle"
	},
	"id1061":{
		"en":"enough",
		"kr":"ase"
	},
	"id1062":{
		"en":"environment",
		"kr":"lanvironnman"
	},
	"id1063":{
		"en":"equipment",
		"kr":"lekipman"
	},
	"id1064":{
		"en":"error",
		"kr":"erer"
	},
	"id1065":{
		"en":"event",
		"kr":"evennman"
	},
	"id1066":{
		"en":"ever",
		"kr":"dezavantaz"
	},
	"id1067":{
		"en":"every",
		"kr":"sak"
	},
	"id1068":{
		"en":"evidence",
		"kr":"prev"
	},
	"id1069":{
		"en":"exact",
		"kr":"exak"
	},
	"id1070":{
		"en":"exaggeration",
		"kr":"exazerasion"
	},
	"id1071":{
		"en":"example",
		"kr":"lexanp"
	},
	"id1072":{
		"en":"except",
		"kr":"exsepte"
	},
	"id1073":{
		"en":"exception",
		"kr":"exsepsion"
	},
	"id1074":{
		"en":"excess",
		"kr":"anplis"
	},
	"id1075":{
		"en":"exchange",
		"kr":"esanz"
	},
	"id1076":{
		"en":"existence",
		"kr":"lexistans"
	},
	"id1077":{
		"en":"exit",
		"kr":"sorti"
	},
	"id1078":{
		"en":"expensive",
		"kr":"ser"
	},
	"id1079":{
		"en":"extremely",
		"kr":"extra or mari"
	},
	"id1080":{
		"en":"fashion",
		"kr":"lamod"
	},
	"id1081":{
		"en":"fishing",
		"kr":"lapes"
	},
	"id1082":{
		"en":"flight",
		"kr":"vol"
	},
	"id1083":{
		"en":"game",
		"kr":"zwe"
	},
	"id1084":{
		"en":"gift",
		"kr":"kado"
	},
	"id1085":{
		"en":"girl",
		"kr":"tifi"
	},
	"id1086":{
		"en":"giver",
		"kr":"doner"
	},
	"id1087":{
		"en":"gold",
		"kr":"lor"
	},
	"id1088":{
		"en":"golden",
		"kr":"dore"
	},
	"id1089":{
		"en":"good",
		"kr":"bon"
	},
	"id1090":{
		"en":"great",
		"kr":"gran or top"
	},
	"id1091":{
		"en":"grief",
		"kr":"sagrin"
	},
	"id1092":{
		"en":"how",
		"kr":"kouma"
	},
	"id1093":{
		"en":"however",
		"kr":"selman"
	},
	"id1094":{
		"en":"hunger",
		"kr":"fin"
	},
	"id1095":{
		"en":"hungry",
		"kr":"gagn fin"
	},
	"id1096":{
		"en":"jealous",
		"kr":"zalou"
	},
	"id1097":{
		"en":"jealousy",
		"kr":"zalouzi"
	},
	"id1098":{
		"en":"journey",
		"kr":"vwayaz"
	},
	"id1099":{
		"en":"just",
		"kr":"zis"
	},
	"id1100":{
		"en":"kick",
		"kr":"kout or pie"
	},
	"id1101":{
		"en":"kind",
		"kr":"bon"
	},
	"id1102":{
		"en":"knot",
		"kr":"ne"
	},
	"id1103":{
		"en":"knowledge",
		"kr":"konesans"
	},
	"id1104":{
		"en":"letter",
		"kr":"let"
	},
	"id1105":{
		"en":"lie",
		"kr":"manti"
	},
	"id1106":{
		"en":"like",
		"kr":"kouma"
	},
	"id1107":{
		"en":"machine",
		"kr":"masinn"
	},
	"id1108":{
		"en":"mail",
		"kr":"kourye"
	},
	"id1109":{
		"en":"main",
		"kr":"prinsipal"
	},
	"id1110":{
		"en":"mainly",
		"kr":"prinsipalman"
	},
	"id1111":{
		"en":"marriage",
		"kr":"maryaz"
	},
	"id1112":{
		"en":"married",
		"kr":"marye"
	},
	"id1113":{
		"en":"may",
		"kr":"kapav"
	},
	"id1114":{
		"en":"maybe",
		"kr":"kitfwa"
	},
	"id1115":{
		"en":"mean",
		"kr":"vedir"
	},
	"id1116":{
		"en":"meaning",
		"kr":"sinifikasion"
	},
	"id1117":{
		"en":"meat",
		"kr":"laviann"
	},
	"id1118":{
		"en":"medicine",
		"kr":"medsinn"
	},
	"id1119":{
		"en":"meeting",
		"kr":"reunion"
	},
	"id1120":{
		"en":"mercy",
		"kr":"pitie"
	},
	"id1121":{
		"en":"mess",
		"kr":"dezord"
	},
	"id1122":{
		"en":"message",
		"kr":"mesaz"
	},
	"id1123":{
		"en":"method",
		"kr":"metod"
	},
	"id1124":{
		"en":"middle",
		"kr":"milie"
	},
	"id1125":{
		"en":"mile",
		"kr":"mil"
	},
	"id1126":{
		"en":"mine",
		"kr":"pou mwa"
	},
	"id1127":{
		"en":"miniature",
		"kr":"miniatir"
	},
	"id1128":{
		"en":"minimum",
		"kr":"minimum"
	},
	"id1129":{
		"en":"miserable",
		"kr":"malere or miserab"
	},
	"id1130":{
		"en":"mistake",
		"kr":"fot"
	},
	"id1131":{
		"en":"most",
		"kr":"laplipar"
	},
	"id1132":{
		"en":"mostly",
		"kr":"sirtou"
	},
	"id1133":{
		"en":"motion",
		"kr":"mouvman"
	},
	"id1134":{
		"en":"motorbike",
		"kr":"moto"
	},
	"id1135":{
		"en":"mouldy",
		"kr":"mwazi"
	},
	"id1136":{
		"en":"mouldy",
		"kr":"gagn mwazi"
	},
	"id1137":{
		"en":"movement",
		"kr":"mouvman"
	},
	"id1138":{
		"en":"muddle",
		"kr":"dezord"
	},
	"id1139":{
		"en":"music",
		"kr":"lamizik"
	},
	"id1140":{
		"en":"must",
		"kr":"bizin or neseser or"
	},
	"id1141":{
		"en":"obligatwar",
		"kr":""
	},
	"id1142":{
		"en":"my",
		"kr":"mo bann"
	},
	"id1143":{
		"en":"myself",
		"kr":"momem or mwa"
	},
	"id1144":{
		"en":"name",
		"kr":"nom"
	},
	"id1145":{
		"en":"narrow",
		"kr":"mins or retresi or sere"
	},
	"id1146":{
		"en":"natural",
		"kr":"natirel"
	},
	"id1147":{
		"en":"naturally",
		"kr":"natirelman"
	},
	"id1148":{
		"en":"naughty",
		"kr":"move"
	},
	"id1149":{
		"en":"neat",
		"kr":"an-ord or prop"
	},
	"id1150":{
		"en":"neatly",
		"kr":"an-ord"
	},
	"id1151":{
		"en":"necessary",
		"kr":"neseser"
	},
	"id1152":{
		"en":"necessity",
		"kr":"nesesite"
	},
	"id1153":{
		"en":"need",
		"kr":"lebezwin"
	},
	"id1154":{
		"en":"negative",
		"kr":"negatif"
	},
	"id1155":{
		"en":"nerve",
		"kr":"kouraz"
	},
	"id1156":{
		"en":"nerves",
		"kr":"trak"
	},
	"id1157":{
		"en":"nervous",
		"kr":"nerve"
	},
	"id1158":{
		"en":"new",
		"kr":"nef or nouvo"
	},
	"id1159":{
		"en":"newspaper",
		"kr":"zournal"
	},
	"id1160":{
		"en":"next",
		"kr":"prosin or swivan"
	},
	"id1161":{
		"en":"nice",
		"kr":"agreab or bon or zoli"
	},
	"id1162":{
		"en":"no",
		"kr":"non"
	},
	"id1163":{
		"en":"noise",
		"kr":"tapaz"
	},
	"id1164":{
		"en":"noisy",
		"kr":"ki fer tapaz"
	},
	"id1165":{
		"en":"none",
		"kr":"okenn"
	},
	"id1166":{
		"en":"nonsense",
		"kr":"ninport"
	},
	"id1167":{
		"en":"normal",
		"kr":"normal"
	},
	"id1168":{
		"en":"nostril",
		"kr":"trou-nene"
	},
	"id1169":{
		"en":"nothing",
		"kr":"nanye"
	},
	"id1170":{
		"en":"nuisance",
		"kr":"nwizans"
	},
	"id1171":{
		"en":"numb",
		"kr":"angourdi"
	},
	"id1172":{
		"en":"nutrient",
		"kr":"aliman nitritif"
	},
	"id1173":{
		"en":"object",
		"kr":"kiksoz or lobze"
	},
	"id1174":{
		"en":"observation",
		"kr":"lobzervasion"
	},
	"id1175":{
		"en":"obstacle",
		"kr":"obstak"
	},
	"id1176":{
		"en":"obstruction",
		"kr":"obstriksion"
	},
	"id1177":{
		"en":"obvious",
		"kr":"evidan"
	},
	"id1178":{
		"en":"occasion",
		"kr":"lokazion"
	},
	"id1179":{
		"en":"odd",
		"kr":"bizar"
	},
	"id1180":{
		"en":"odour",
		"kr":"loder"
	},
	"id1181":{
		"en":"off",
		"kr":"tengn"
	},
	"id1182":{
		"en":"offence",
		"kr":"ofans"
	},
	"id1183":{
		"en":"offensive",
		"kr":"ofansif"
	},
	"id1184":{
		"en":"offer",
		"kr":"lof or of"
	},
	"id1185":{
		"en":"office",
		"kr":"biro"
	},
	"id1186":{
		"en":"official",
		"kr":"ofisiel"
	},
	"id1187":{
		"en":"officially",
		"kr":"ofisielman"
	},
	"id1188":{
		"en":"oil",
		"kr":"delwil"
	},
	"id1189":{
		"en":"old",
		"kr":"vie"
	},
	"id1190":{
		"en":"on",
		"kr":"lor"
	},
	"id1191":{
		"en":"oneself",
		"kr":"limem"
	},
	"id1192":{
		"en":"only",
		"kr":"zis"
	},
	"id1193":{
		"en":"open",
		"kr":"ouver"
	},
	"id1194":{
		"en":"opening",
		"kr":"ouvertir"
	},
	"id1195":{
		"en":"openly",
		"kr":"ouvertman"
	},
	"id1196":{
		"en":"opportunity",
		"kr":"loportinite"
	},
	"id1197":{
		"en":"opposite",
		"kr":"kontrer"
	},
	"id1198":{
		"en":"option",
		"kr":"opsion"
	},
	"id1199":{
		"en":"or",
		"kr":"ouswa or swa"
	},
	"id1200":{
		"en":"ordinary",
		"kr":"ordiner"
	},
	"id1201":{
		"en":"organisation",
		"kr":"lorganizasion"
	},
	"id1202":{
		"en":"organiser",
		"kr":"organizateur"
	},
	"id1203":{
		"en":"original",
		"kr":"orizinal"
	},
	"id1204":{
		"en":"other",
		"kr":"lot"
	},
	"id1205":{
		"en":"our",
		"kr":"nou or pou nou"
	},
	"id1206":{
		"en":"out",
		"kr":"deor"
	},
	"id1207":{
		"en":"outsider",
		"kr":"etranze"
	},
	"id1208":{
		"en":"oval",
		"kr":"oval"
	},
	"id1209":{
		"en":"owe",
		"kr":"dwa"
	},
	"id1210":{
		"en":"owner",
		"kr":"proprieter"
	},
	"id1211":{
		"en":"oxygen",
		"kr":"loxizenn"
	},
	"id1212":{
		"en":"packet",
		"kr":"pake"
	},
	"id1213":{
		"en":"page",
		"kr":"paz"
	},
	"id1214":{
		"en":"pain",
		"kr":"douler"
	},
	"id1215":{
		"en":"painful",
		"kr":"penib"
	},
	"id1216":{
		"en":"paint",
		"kr":"lapintir"
	},
	"id1217":{
		"en":"pair",
		"kr":"per"
	},
	"id1218":{
		"en":"pale",
		"kr":"pal"
	},
	"id1219":{
		"en":"panel",
		"kr":"pano"
	},
	"id1220":{
		"en":"panic",
		"kr":"panik"
	},
	"id1221":{
		"en":"paper",
		"kr":"papie"
	},
	"id1222":{
		"en":"paradise",
		"kr":"paradi"
	},
	"id1223":{
		"en":"paragraph",
		"kr":"paragraf"
	},
	"id1224":{
		"en":"parallel",
		"kr":"paralel"
	},
	"id1225":{
		"en":"parent",
		"kr":"paran"
	},
	"id1226":{
		"en":"part",
		"kr":"par"
	},
	"id1227":{
		"en":"part",
		"kr":"an parti"
	},
	"id1228":{
		"en":"particular",
		"kr":"partikilie"
	},
	"id1229":{
		"en":"partition",
		"kr":"klwazon or partision"
	},
	"id1230":{
		"en":"party",
		"kr":"fet"
	},
	"id1231":{
		"en":"passage",
		"kr":"pasaz"
	},
	"id1232":{
		"en":"passenger",
		"kr":"pasaze"
	},
	"id1233":{
		"en":"passport",
		"kr":"paspor"
	},
	"id1234":{
		"en":"past",
		"kr":"lepase"
	},
	"id1235":{
		"en":"path",
		"kr":"santie or semin or sime"
	},
	"id1236":{
		"en":"patience",
		"kr":"patians"
	},
	"id1237":{
		"en":"pattern",
		"kr":"patern"
	},
	"id1238":{
		"en":"pause",
		"kr":"poz or silans"
	},
	"id1239":{
		"en":"pavement",
		"kr":"trotwar"
	},
	"id1240":{
		"en":"paw",
		"kr":"lapat"
	},
	"id1241":{
		"en":"payment",
		"kr":"peyman"
	},
	"id1242":{
		"en":"peace",
		"kr":"lape"
	},
	"id1243":{
		"en":"peaceful",
		"kr":"kalm or trankil"
	},
	"id1244":{
		"en":"pear",
		"kr":"pwar"
	},
	"id1245":{
		"en":"pedestrian",
		"kr":"pieton"
	},
	"id1246":{
		"en":"peg",
		"kr":"pins"
	},
	"id1247":{
		"en":"pen",
		"kr":"plim"
	},
	"id1248":{
		"en":"pencil",
		"kr":"kreyon"
	},
	"id1249":{
		"en":"pencil",
		"kr":"case plimie"
	},
	"id1250":{
		"en":"pencil",
		"kr":"sharpener fitwar"
	},
	"id1251":{
		"en":"perfect",
		"kr":"parfe"
	},
	"id1252":{
		"en":"perfume",
		"kr":"parfime"
	},
	"id1253":{
		"en":"perhaps",
		"kr":"kapav"
	},
	"id1254":{
		"en":"pester",
		"kr":"manz lavi"
	},
	"id1255":{
		"en":"phone",
		"kr":"portab"
	},
	"id1256":{
		"en":"photo",
		"kr":"foto"
	},
	"id1257":{
		"en":"picture",
		"kr":"tablo"
	},
	"id1258":{
		"en":"piece",
		"kr":"morso"
	},
	"id1259":{
		"en":"pile",
		"kr":"enn ta"
	},
	"id1260":{
		"en":"pity",
		"kr":"pitie"
	},
	"id1261":{
		"en":"plan",
		"kr":"plan"
	},
	"id1262":{
		"en":"plane",
		"kr":"avion"
	},
	"id1263":{
		"en":"plaster",
		"kr":"plak"
	},
	"id1264":{
		"en":"plastic",
		"kr":"plastik"
	},
	"id1265":{
		"en":"plate",
		"kr":"pla"
	},
	"id1266":{
		"en":"platform",
		"kr":"lestrad"
	},
	"id1267":{
		"en":"pleasant",
		"kr":"agreab"
	},
	"id1268":{
		"en":"please",
		"kr":"silvouple"
	},
	"id1269":{
		"en":"please",
		"kr":"silteple"
	},
	"id1270":{
		"en":"pleasure",
		"kr":"plezir"
	},
	"id1271":{
		"en":"pliers",
		"kr":"pins"
	},
	"id1272":{
		"en":"point",
		"kr":"pwin"
	},
	"id1273":{
		"en":"poison",
		"kr":"pwazon"
	},
	"id1274":{
		"en":"pole",
		"kr":"polone"
	},
	"id1275":{
		"en":"police",
		"kr":"lapolis"
	},
	"id1276":{
		"en":"poor",
		"kr":"pov"
	},
	"id1277":{
		"en":"portion",
		"kr":"porsion"
	},
	"id1278":{
		"en":"position",
		"kr":"pozision"
	},
	"id1279":{
		"en":"possession",
		"kr":"posesion"
	},
	"id1280":{
		"en":"possible",
		"kr":"posib"
	},
	"id1281":{
		"en":"post",
		"kr":"lapos"
	},
	"id1282":{
		"en":"post",
		"kr":"travay"
	},
	"id1283":{
		"en":"powder",
		"kr":"lapoud"
	},
	"id1284":{
		"en":"power",
		"kr":"pouvwar"
	},
	"id1285":{
		"en":"praise",
		"kr":"eloz"
	},
	"id1286":{
		"en":"prayer",
		"kr":"lapriyer"
	},
	"id1287":{
		"en":"precise",
		"kr":"presi"
	},
	"id1288":{
		"en":"preparation",
		"kr":"preparasion"
	},
	"id1289":{
		"en":"prescription",
		"kr":"lordonans"
	},
	"id1290":{
		"en":"presence",
		"kr":"prezans"
	},
	"id1291":{
		"en":"present",
		"kr":"prezan"
	},
	"id1292":{
		"en":"press",
		"kr":"lapres"
	},
	"id1293":{
		"en":"price",
		"kr":"pri"
	},
	"id1294":{
		"en":"pride",
		"kr":"fierte"
	},
	"id1295":{
		"en":"priority",
		"kr":"priorite"
	},
	"id1296":{
		"en":"private",
		"kr":"prive"
	},
	"id1297":{
		"en":"problem",
		"kr":"problem"
	},
	"id1298":{
		"en":"procedure",
		"kr":"prosedir"
	},
	"id1299":{
		"en":"process",
		"kr":"prosesis"
	},
	"id1300":{
		"en":"profit",
		"kr":"profi"
	},
	"id1301":{
		"en":"property",
		"kr":"propriete"
	},
	"id1302":{
		"en":"protection",
		"kr":"proteksion"
	},
	"id1303":{
		"en":"public",
		"kr":"piblik"
	},
	"id1304":{
		"en":"publicity",
		"kr":"piblisite or reklam"
	},
	"id1305":{
		"en":"punch",
		"kr":"koudpwin"
	},
	"id1306":{
		"en":"pure",
		"kr":"pir"
	},
	"id1307":{
		"en":"purity",
		"kr":"pirte"
	},
	"id1308":{
		"en":"purple",
		"kr":"mov"
	},
	"id1309":{
		"en":"purpose",
		"kr":"lintansion"
	},
	"id1310":{
		"en":"qualification",
		"kr":"kalifikasion"
	},
	"id1311":{
		"en":"quality",
		"kr":"kalite"
	},
	"id1312":{
		"en":"quarrel",
		"kr":"bagar"
	},
	"id1313":{
		"en":"question",
		"kr":"kestion"
	},
	"id1314":{
		"en":"queue",
		"kr":"lake"
	},
	"id1315":{
		"en":"quick",
		"kr":"rapid"
	},
	"id1316":{
		"en":"quickly",
		"kr":"vit"
	},
	"id1317":{
		"en":"quiet",
		"kr":"trankil"
	},
	"id1318":{
		"en":"race",
		"kr":"lekours"
	},
	"id1319":{
		"en":"radio",
		"kr":"radio"
	},
	"id1320":{
		"en":"rag",
		"kr":"sinfon"
	},
	"id1321":{
		"en":"rage",
		"kr":"laraz"
	},
	"id1322":{
		"en":"rather",
		"kr":"plito"
	},
	"id1323":{
		"en":"raw",
		"kr":"kri"
	},
	"id1324":{
		"en":"razor",
		"kr":"razwar"
	},
	"id1325":{
		"en":"reaction",
		"kr":"reaksion"
	},
	"id1326":{
		"en":"reason",
		"kr":"la rezon"
	},
	"id1327":{
		"en":"reasoning",
		"kr":"rezonnman"
	},
	"id1328":{
		"en":"receipt",
		"kr":"resi"
	},
	"id1329":{
		"en":"recent",
		"kr":"resan"
	},
	"id1330":{
		"en":"recovery",
		"kr":"retablisman"
	},
	"id1331":{
		"en":"reform",
		"kr":"reform"
	},
	"id1332":{
		"en":"regular",
		"kr":"regilie"
	},
	"id1333":{
		"en":"release",
		"kr":"liberasion"
	},
	"id1334":{
		"en":"religion",
		"kr":"relizion"
	},
	"id1335":{
		"en":"request",
		"kr":"reket"
	},
	"id1336":{
		"en":"respect",
		"kr":"respe"
	},
	"id1337":{
		"en":"respectable",
		"kr":"respektab"
	},
	"id1338":{
		"en":"responsible",
		"kr":"responsab"
	},
	"id1339":{
		"en":"rhythm",
		"kr":"ritm"
	},
	"id1340":{
		"en":"rib",
		"kr":"kot"
	},
	"id1341":{
		"en":"rich",
		"kr":"ris"
	},
	"id1342":{
		"en":"ring",
		"kr":"bag"
	},
	"id1343":{
		"en":"river",
		"kr":"larivier"
	},
	"id1344":{
		"en":"riverbank",
		"kr":"bor larivier"
	},
	"id1345":{
		"en":"road",
		"kr":"semin or sime"
	},
	"id1346":{
		"en":"rock",
		"kr":"ros"
	},
	"id1347":{
		"en":"rope",
		"kr":"lakord"
	},
	"id1348":{
		"en":"rough",
		"kr":"brouyon"
	},
	"id1349":{
		"en":"round",
		"kr":"ron"
	},
	"id1350":{
		"en":"rubbish",
		"kr":"salte"
	},
	"id1351":{
		"en":"rude",
		"kr":"malelve"
	},
	"id1352":{
		"en":"ruin",
		"kr":"larwinn"
	},
	"id1353":{
		"en":"rust",
		"kr":"larouy"
	},
	"id1354":{
		"en":"sad",
		"kr":"tris"
	},
	"id1355":{
		"en":"safety",
		"kr":"sekirite"
	},
	"id1356":{
		"en":"salt",
		"kr":"disel"
	},
	"id1357":{
		"en":"same",
		"kr":"parey"
	},
	"id1358":{
		"en":"sand",
		"kr":"disab"
	},
	"id1359":{
		"en":"sauce",
		"kr":"lasos"
	},
	"id1360":{
		"en":"school",
		"kr":"lekol"
	},
	"id1361":{
		"en":"science",
		"kr":"sians"
	},
	"id1362":{
		"en":"screen",
		"kr":"lekran"
	},
	"id1363":{
		"en":"seat",
		"kr":"siez"
	},
	"id1364":{
		"en":"secret",
		"kr":"sekre"
	},
	"id1365":{
		"en":"selection",
		"kr":"seleksion"
	},
	"id1366":{
		"en":"self",
		"kr":"mwa"
	},
	"id1367":{
		"en":"serious",
		"kr":"serye"
	},
	"id1368":{
		"en":"shame",
		"kr":"laont"
	},
	"id1369":{
		"en":"shape",
		"kr":"form"
	},
	"id1370":{
		"en":"sharp",
		"kr":"fite"
	},
	"id1371":{
		"en":"shelf",
		"kr":"letazer"
	},
	"id1372":{
		"en":"shell",
		"kr":"koki"
	},
	"id1373":{
		"en":"shiny",
		"kr":"briyan"
	},
	"id1374":{
		"en":"shiver",
		"kr":"frison"
	},
	"id1375":{
		"en":"shock",
		"kr":"sok"
	},
	"id1376":{
		"en":"shop",
		"kr":"laboutik"
	},
	"id1377":{
		"en":"short",
		"kr":"kourt"
	},
	"id1378":{
		"en":"sick",
		"kr":"malad"
	},
	"id1379":{
		"en":"sickness",
		"kr":"maladi"
	},
	"id1380":{
		"en":"side",
		"kr":"kote"
	},
	"id1381":{
		"en":"sieve",
		"kr":"taminn"
	},
	"id1382":{
		"en":"sigh",
		"kr":"soupir"
	},
	"id1383":{
		"en":"sign",
		"kr":"sign"
	},
	"id1384":{
		"en":"signature",
		"kr":"signatir"
	},
	"id1385":{
		"en":"silence",
		"kr":"silans"
	},
	"id1386":{
		"en":"silent",
		"kr":"trankil"
	},
	"id1387":{
		"en":"silver",
		"kr":"larzan"
	},
	"id1388":{
		"en":"simple",
		"kr":"simp"
	},
	"id1389":{
		"en":"sincere",
		"kr":"sinser"
	},
	"id1390":{
		"en":"sincerity",
		"kr":"sinserite"
	},
	"id1391":{
		"en":"sip",
		"kr":"ti-gorze"
	},
	"id1392":{
		"en":"slice",
		"kr":"trans"
	},
	"id1393":{
		"en":"slim",
		"kr":"mins"
	},
	"id1394":{
		"en":"slope",
		"kr":"lapant"
	},
	"id1395":{
		"en":"slow",
		"kr":"dousman"
	},
	"id1396":{
		"en":"smart",
		"kr":"elegan"
	},
	"id1397":{
		"en":"smell",
		"kr":"loder"
	},
	"id1398":{
		"en":"smoke",
		"kr":"lafime"
	},
	"id1399":{
		"en":"smooth",
		"kr":"lis"
	},
	"id1400":{
		"en":"soap",
		"kr":"savon"
	},
	"id1401":{
		"en":"soft",
		"kr":"mol or mou"
	},
	"id1402":{
		"en":"sole",
		"kr":"semel"
	},
	"id1403":{
		"en":"solid",
		"kr":"solid"
	},
	"id1404":{
		"en":"soluble",
		"kr":"solib"
	},
	"id1405":{
		"en":"something",
		"kr":"zafer"
	},
	"id1406":{
		"en":"song",
		"kr":"sante"
	},
	"id1407":{
		"en":"sort",
		"kr":"espes"
	},
	"id1408":{
		"en":"soul",
		"kr":"lespri"
	},
	"id1409":{
		"en":"sound",
		"kr":"son"
	},
	"id1410":{
		"en":"sour",
		"kr":"eg"
	},
	"id1411":{
		"en":"special",
		"kr":"spesial"
	},
	"id1412":{
		"en":"speech",
		"kr":"diskour"
	},
	"id1413":{
		"en":"spirit",
		"kr":"lespri"
	},
	"id1414":{
		"en":"sponge",
		"kr":"leponz"
	},
	"id1415":{
		"en":"sport",
		"kr":"spor"
	},
	"id1416":{
		"en":"spot",
		"kr":"tas"
	},
	"id1417":{
		"en":"spring",
		"kr":"printan"
	},
	"id1418":{
		"en":"square",
		"kr":"kare"
	},
	"id1419":{
		"en":"star",
		"kr":"zetwal"
	},
	"id1420":{
		"en":"steam",
		"kr":"vaper"
	},
	"id1421":{
		"en":"steel",
		"kr":"lasie"
	},
	"id1422":{
		"en":"step",
		"kr":"pa"
	},
	"id1423":{
		"en":"sticky",
		"kr":"kolan"
	},
	"id1424":{
		"en":"stiff",
		"kr":"red"
	},
	"id1425":{
		"en":"still",
		"kr":"ankor"
	},
	"id1426":{
		"en":"stone",
		"kr":"ros"
	},
	"id1427":{
		"en":"story",
		"kr":"zistwar"
	},
	"id1428":{
		"en":"straight",
		"kr":"drwat"
	},
	"id1429":{
		"en":"strange",
		"kr":"etranz"
	},
	"id1430":{
		"en":"stranger",
		"kr":"etranze"
	},
	"id1431":{
		"en":"street",
		"kr":"lari"
	},
	"id1432":{
		"en":"strong",
		"kr":"for"
	},
	"id1433":{
		"en":"structure",
		"kr":"striktir"
	},
	"id1434":{
		"en":"student",
		"kr":"etidian"
	},
	"id1435":{
		"en":"stupid",
		"kr":"kouyon"
	},
	"id1436":{
		"en":"substance",
		"kr":"sibstans"
	},
	"id1437":{
		"en":"sudden",
		"kr":"enn kout"
	},
	"id1438":{
		"en":"sugar",
		"kr":"disik"
	},
	"id1439":{
		"en":"suggestion",
		"kr":"sizestion"
	},
	"id1440":{
		"en":"superb",
		"kr":"siper"
	},
	"id1441":{
		"en":"surely",
		"kr":"sirman"
	},
	"id1442":{
		"en":"surprise",
		"kr":"sirpriz"
	},
	"id1443":{
		"en":"sweet",
		"kr":"dou"
	},
	"id1444":{
		"en":"talk",
		"kr":"kozri"
	},
	"id1445":{
		"en":"tall",
		"kr":"long"
	},
	"id1446":{
		"en":"tasty",
		"kr":"bon"
	},
	"id1447":{
		"en":"teacher",
		"kr":"profeser"
	},
	"id1448":{
		"en":"team",
		"kr":"lekip"
	},
	"id1449":{
		"en":"tear",
		"kr":"larm"
	},
	"id1450":{
		"en":"teeth",
		"kr":"ledan"
	},
	"id1451":{
		"en":"temper",
		"kr":"karakter"
	},
	"id1452":{
		"en":"temperature",
		"kr":"tanperatir"
	},
	"id1453":{
		"en":"tendency",
		"kr":"tandans"
	},
	"id1454":{
		"en":"that",
		"kr":"sa"
	},
	"id1455":{
		"en":"that",
		"kr":" seki"
	},
	"id1456":{
		"en":"theatre",
		"kr":"teat"
	},
	"id1457":{
		"en":"theory",
		"kr":"teori"
	},
	"id1458":{
		"en":"thick",
		"kr":"epe"
	},
	"id1459":{
		"en":"thickness",
		"kr":"lepeser"
	},
	"id1460":{
		"en":"thief",
		"kr":"voler"
	},
	"id1461":{
		"en":"thin",
		"kr":"mins"
	},
	"id1462":{
		"en":"thing",
		"kr":"kiksoz"
	},
	"id1463":{
		"en":"thirst",
		"kr":"laswaf or swaf"
	},
	"id1464":{
		"en":"thirsty",
		"kr":"gagn swaf"
	},
	"id1465":{
		"en":"this",
		"kr":"sa"
	},
	"id1466":{
		"en":"threat",
		"kr":"menas"
	},
	"id1467":{
		"en":"through",
		"kr":"atraver"
	},
	"id1468":{
		"en":"tick",
		"kr":"rayt"
	},
	"id1469":{
		"en":"ticket",
		"kr":"tiket"
	},
	"id1470":{
		"en":"tidy",
		"kr":"an-ord"
	},
	"id1471":{
		"en":"tight",
		"kr":"sere"
	},
	"id1472":{
		"en":"tin",
		"kr":"bwat konserv"
	},
	"id1473":{
		"en":"tiny",
		"kr":"miniskil"
	},
	"id1474":{
		"en":"tip",
		"kr":"bout"
	},
	"id1475":{
		"en":"tire",
		"kr":"larou"
	},
	"id1476":{
		"en":"tired",
		"kr":"fatige"
	},
	"id1477":{
		"en":"tiredness",
		"kr":"lafatigue"
	},
	"id1478":{
		"en":"together",
		"kr":"ansam"
	},
	"id1479":{
		"en":"tool",
		"kr":"zouti"
	},
	"id1480":{
		"en":"top",
		"kr":"some"
	},
	"id1481":{
		"en":"torch",
		"kr":"tors"
	},
	"id1482":{
		"en":"tough",
		"kr":"dir"
	},
	"id1483":{
		"en":"train",
		"kr":"trin"
	},
	"id1484":{
		"en":"transport",
		"kr":"transpor"
	},
	"id1485":{
		"en":"trap",
		"kr":"pieze"
	},
	"id1486":{
		"en":"trash",
		"kr":"salte"
	},
	"id1487":{
		"en":"tray",
		"kr":"plato"
	},
	"id1488":{
		"en":"treasury",
		"kr":"trezor"
	},
	"id1489":{
		"en":"trick",
		"kr":"trik"
	},
	"id1490":{
		"en":"trip",
		"kr":"exkirsion"
	},
	"id1491":{
		"en":"trouble",
		"kr":"problem"
	},
	"id1492":{
		"en":"true",
		"kr":"vre"
	},
	"id1493":{
		"en":"trust",
		"kr":"konfians"
	},
	"id1494":{
		"en":"truth",
		"kr":"verite"
	},
	"id1495":{
		"en":"try",
		"kr":"seye, sey"
	},
	"id1496":{
		"en":"type",
		"kr":"tip"
	},
	"id1497":{
		"en":"ugly",
		"kr":"vilin"
	},
	"id1498":{
		"en":"ultimate",
		"kr":"final"
	},
	"id1499":{
		"en":"unbalance",
		"kr":"dezekilibre"
	},
	"id1500":{
		"en":"uncomfortable",
		"kr":"infonfortab"
	},
	"id1501":{
		"en":"unlucky",
		"kr":"malsanse"
	},
	"id1502":{
		"en":"unsure",
		"kr":"insertin"
	},
	"id1503":{
		"en":"untidy",
		"kr":"an dezord"
	},
	"id1504":{
		"en":"until",
		"kr":"ziska"
	},
	"id1505":{
		"en":"upside",
		"kr":"down anba-lao"
	},
	"id1506":{
		"en":"useful",
		"kr":"itil"
	},
	"id1507":{
		"en":"usual",
		"kr":"abitiel"
	},
	"id1508":{
		"en":"utility",
		"kr":"itilite"
	},
	"id1509":{
		"en":"validity",
		"kr":"validite"
	},
	"id1510":{
		"en":"value",
		"kr":"valer"
	},
	"id1511":{
		"en":"vapour",
		"kr":"lavaper"
	},
	"id1512":{
		"en":"variant",
		"kr":"varyant"
	},
	"id1513":{
		"en":"variation",
		"kr":"varyasion"
	},
	"id1514":{
		"en":"variety",
		"kr":"varyete"
	},
	"id1515":{
		"en":"various",
		"kr":"boukou or diferan"
	},
	"id1516":{
		"en":"vertical",
		"kr":"vertikal"
	},
	"id1517":{
		"en":"vest",
		"kr":"zile"
	},
	"id1518":{
		"en":"vision",
		"kr":"vi"
	},
	"id1519":{
		"en":"visitor",
		"kr":"viziter"
	},
	"id1520":{
		"en":"voyage",
		"kr":"vwayaz"
	},
	"id1521":{
		"en":"wage",
		"kr":"lapey"
	},
	"id1522":{
		"en":"war",
		"kr":"lager"
	},
	"id1523":{
		"en":"warm",
		"kr":"tied"
	},
	"id1524":{
		"en":"wave",
		"kr":"vag"
	},
	"id1525":{
		"en":"weak",
		"kr":"feb"
	},
	"id1526":{
		"en":"weakness",
		"kr":"febles"
	},
	"id1527":{
		"en":"wealth",
		"kr":"rises"
	},
	"id1528":{
		"en":"wedding",
		"kr":"maryaz"
	},
	"id1529":{
		"en":"weight",
		"kr":"pwa"
	},
	"id1530":{
		"en":"weird",
		"kr":"bizar"
	},
	"id1531":{
		"en":"well",
		"kr":"bien"
	},
	"id1532":{
		"en":"well",
		"kr":"known renome"
	},
	"id1533":{
		"en":"wet",
		"kr":"mouye"
	},
	"id1534":{
		"en":"what",
		"kr":"ki"
	},
	"id1535":{
		"en":"wheel",
		"kr":"larou"
	},
	"id1536":{
		"en":"wheelbarrow",
		"kr":"bouret"
	},
	"id1537":{
		"en":"when",
		"kr":"kan"
	},
	"id1538":{
		"en":"where",
		"kr":"kot"
	},
	"id1539":{
		"en":"who",
		"kr":"ki"
	},
	"id1540":{
		"en":"who",
		"kr":"ki sann-la"
	},
	"id1541":{
		"en":"why",
		"kr":"kifer"
	},
	"id1542":{
		"en":"wide",
		"kr":"larz"
	},
	"id1543":{
		"en":"wild",
		"kr":"sovaz"
	},
	"id1544":{
		"en":"wing",
		"kr":"lezel"
	},
	"id1545":{
		"en":"wise",
		"kr":"saz"
	},
	"id1546":{
		"en":"wish",
		"kr":"ve"
	},
	"id1547":{
		"en":"with",
		"kr":"ar or avek or ek"
	},
	"id1548":{
		"en":"without",
		"kr":"san"
	},
	"id1549":{
		"en":"wood",
		"kr":"dibwa"
	},
	"id1550":{
		"en":"wooden",
		"kr":"an dibwa"
	},
	"id1551":{
		"en":"wool",
		"kr":"lalenn"
	},
	"id1552":{
		"en":"word",
		"kr":"mo"
	},
	"id1553":{
		"en":"worker",
		"kr":"travayer"
	},
	"id1554":{
		"en":"wrapper",
		"kr":"anbalaz"
	},
	"id1555":{
		"en":"wrong",
		"kr":"pa bon"
	},
	"id1556":{
		"en":"yes",
		"kr":"wi"
	},
	"id1557":{
		"en":"young",
		"kr":"zenn"
	},
	"id1558":{
		"en":"youth",
		"kr":"zenes"
	}
  }
}
